{
"meta":{"test_sets":[],"test_metrics":[],"learn_metrics":[{"best_value":"Min","name":"Logloss"}],"launch_mode":"Train","parameters":"","iteration_count":1000,"learn_sets":["learn"],"name":"experiment"},
"iterations":[
{"learn":[0.6912124713],"iteration":0,"passed_time":0.0111788402,"remaining_time":11.16766136},
{"learn":[0.6889489703],"iteration":1,"passed_time":0.0232254175,"remaining_time":11.58948333},
{"learn":[0.6868760303],"iteration":2,"passed_time":0.03623410626,"remaining_time":12.04180131},
{"learn":[0.6848431317],"iteration":3,"passed_time":0.04815916365,"remaining_time":11.99163175},
{"learn":[0.6830460617],"iteration":4,"passed_time":0.06231855787,"remaining_time":12.40139302},
{"learn":[0.6812582168],"iteration":5,"passed_time":0.07488245993,"remaining_time":12.40552753},
{"learn":[0.6795927433],"iteration":6,"passed_time":0.0866834654,"remaining_time":12.29666873},
{"learn":[0.6778772695],"iteration":7,"passed_time":0.09866534263,"remaining_time":12.23450249},
{"learn":[0.6761850935],"iteration":8,"passed_time":0.1118310271,"remaining_time":12.31383865},
{"learn":[0.6746005631],"iteration":9,"passed_time":0.1411010208,"remaining_time":13.96900106},
{"learn":[0.672883299],"iteration":10,"passed_time":0.1535670832,"remaining_time":13.80707684},
{"learn":[0.6710526743],"iteration":11,"passed_time":0.1648795682,"remaining_time":13.57508445},
{"learn":[0.6694959277],"iteration":12,"passed_time":0.1770117396,"remaining_time":13.43927592},
{"learn":[0.6681431417],"iteration":13,"passed_time":0.1893615196,"remaining_time":13.33646131},
{"learn":[0.6667333778],"iteration":14,"passed_time":0.2024978753,"remaining_time":13.29736048},
{"learn":[0.6651197033],"iteration":15,"passed_time":0.2146232389,"remaining_time":13.19932919},
{"learn":[0.6637139504],"iteration":16,"passed_time":0.2278963788,"remaining_time":13.17777296},
{"learn":[0.6624087945],"iteration":17,"passed_time":0.2408886529,"remaining_time":13.14181429},
{"learn":[0.6612546516],"iteration":18,"passed_time":0.2537955866,"remaining_time":13.10386687},
{"learn":[0.6598745329],"iteration":19,"passed_time":0.2650563274,"remaining_time":12.98776005},
{"learn":[0.6585517123],"iteration":20,"passed_time":0.2772100464,"remaining_time":12.92326836},
{"learn":[0.6574740915],"iteration":21,"passed_time":0.2887380553,"remaining_time":12.835719},
{"learn":[0.6564415023],"iteration":22,"passed_time":0.3005264853,"remaining_time":12.76584244},
{"learn":[0.6550928722],"iteration":23,"passed_time":0.3117266311,"remaining_time":12.676883},
{"learn":[0.6540919005],"iteration":24,"passed_time":0.3355406321,"remaining_time":13.08608465},
{"learn":[0.6531742329],"iteration":25,"passed_time":0.3456415373,"remaining_time":12.94826374},
{"learn":[0.6521403433],"iteration":26,"passed_time":0.3574223819,"remaining_time":12.88044361},
{"learn":[0.6509891931],"iteration":27,"passed_time":0.3696838077,"remaining_time":12.83330933},
{"learn":[0.650042212],"iteration":28,"passed_time":0.381688013,"remaining_time":12.77996761},
{"learn":[0.6490677576],"iteration":29,"passed_time":0.3928568253,"remaining_time":12.70237068},
{"learn":[0.6480187428],"iteration":30,"passed_time":0.4054630354,"remaining_time":12.67398972},
{"learn":[0.6471325888],"iteration":31,"passed_time":0.4176833207,"remaining_time":12.63492045},
{"learn":[0.6463579152],"iteration":32,"passed_time":0.4292679046,"remaining_time":12.57885042},
{"learn":[0.6454548081],"iteration":33,"passed_time":0.4407577771,"remaining_time":12.52270626},
{"learn":[0.6445174265],"iteration":34,"passed_time":0.4532191231,"remaining_time":12.49589868},
{"learn":[0.6437205786],"iteration":35,"passed_time":0.4663606707,"remaining_time":12.4881024},
{"learn":[0.6429301545],"iteration":36,"passed_time":0.4793670227,"remaining_time":12.47649846},
{"learn":[0.6421953619],"iteration":37,"passed_time":0.4907912345,"remaining_time":12.42476757},
{"learn":[0.6414270226],"iteration":38,"passed_time":0.5032303282,"remaining_time":12.40011142},
{"learn":[0.6406484736],"iteration":39,"passed_time":0.5154393601,"remaining_time":12.37054464},
{"learn":[0.6398100651],"iteration":40,"passed_time":0.5268337247,"remaining_time":12.32276932},
{"learn":[0.6389119318],"iteration":41,"passed_time":0.5384451966,"remaining_time":12.28167853},
{"learn":[0.6381483908],"iteration":42,"passed_time":0.5498618942,"remaining_time":12.23762402},
{"learn":[0.6374077385],"iteration":43,"passed_time":0.561332874,"remaining_time":12.19623244},
{"learn":[0.6367340087],"iteration":44,"passed_time":0.5737082699,"remaining_time":12.1753644},
{"learn":[0.6357703274],"iteration":45,"passed_time":0.5866975749,"remaining_time":12.16759753},
{"learn":[0.6350343829],"iteration":46,"passed_time":0.6018635557,"remaining_time":12.20374401},
{"learn":[0.6344354845],"iteration":47,"passed_time":0.6166243987,"remaining_time":12.22971724},
{"learn":[0.6338150861],"iteration":48,"passed_time":0.6551195235,"remaining_time":12.71466667},
{"learn":[0.6330771583],"iteration":49,"passed_time":0.6704223131,"remaining_time":12.73802395},
{"learn":[0.6324773465],"iteration":50,"passed_time":0.6850826146,"remaining_time":12.74790983},
{"learn":[0.631896376],"iteration":51,"passed_time":0.6996228136,"remaining_time":12.75466206},
{"learn":[0.6313325862],"iteration":52,"passed_time":0.7130533419,"remaining_time":12.7407833},
{"learn":[0.6306469712],"iteration":53,"passed_time":0.7275042339,"remaining_time":12.74479639},
{"learn":[0.6300782957],"iteration":54,"passed_time":0.7396880388,"remaining_time":12.70918539},
{"learn":[0.6294105377],"iteration":55,"passed_time":0.7688230493,"remaining_time":12.96015997},
{"learn":[0.6290352557],"iteration":56,"passed_time":0.7823818854,"remaining_time":12.9436161},
{"learn":[0.6284527529],"iteration":57,"passed_time":0.7949481109,"remaining_time":12.9110538},
{"learn":[0.6278935307],"iteration":58,"passed_time":0.8080814734,"remaining_time":12.88821469},
{"learn":[0.6273667012],"iteration":59,"passed_time":0.8207065813,"remaining_time":12.85773644},
{"learn":[0.626892862],"iteration":60,"passed_time":0.8342107201,"remaining_time":12.84137486},
{"learn":[0.6263804086],"iteration":61,"passed_time":0.8471947391,"remaining_time":12.81723654},
{"learn":[0.6259033488],"iteration":62,"passed_time":0.8595001996,"remaining_time":12.78336011},
{"learn":[0.6252479243],"iteration":63,"passed_time":0.8716403736,"remaining_time":12.74774046},
{"learn":[0.6247963211],"iteration":64,"passed_time":0.8848385736,"remaining_time":12.72806256},
{"learn":[0.6244041381],"iteration":65,"passed_time":0.9037200864,"remaining_time":12.7890085},
{"learn":[0.6239286615],"iteration":66,"passed_time":0.9198856881,"remaining_time":12.80975145},
{"learn":[0.6233265885],"iteration":67,"passed_time":0.9358820419,"remaining_time":12.82708916},
{"learn":[0.6230194141],"iteration":68,"passed_time":0.9492316057,"remaining_time":12.80774819},
{"learn":[0.6225796504],"iteration":69,"passed_time":0.9782734818,"remaining_time":12.99706197},
{"learn":[0.6221975797],"iteration":70,"passed_time":0.9921407659,"remaining_time":12.98167284},
{"learn":[0.6217621083],"iteration":71,"passed_time":1.005739541,"remaining_time":12.9628652},
{"learn":[0.6214803329],"iteration":72,"passed_time":1.017963205,"remaining_time":12.92673824},
{"learn":[0.6210647281],"iteration":73,"passed_time":1.031695664,"remaining_time":12.91013763},
{"learn":[0.6205888349],"iteration":74,"passed_time":1.044959037,"remaining_time":12.88782812},
{"learn":[0.6200754263],"iteration":75,"passed_time":1.057782658,"remaining_time":12.86041021},
{"learn":[0.6196430146],"iteration":76,"passed_time":1.071118991,"remaining_time":12.83951725},
{"learn":[0.6193425299],"iteration":77,"passed_time":1.083293094,"remaining_time":12.8050799},
{"learn":[0.6188628096],"iteration":78,"passed_time":1.096896153,"remaining_time":12.78786528},
{"learn":[0.6181014339],"iteration":79,"passed_time":1.111606044,"remaining_time":12.78346951},
{"learn":[0.6175134305],"iteration":80,"passed_time":1.126413324,"remaining_time":12.77992401},
{"learn":[0.6171577943],"iteration":81,"passed_time":1.140803361,"remaining_time":12.77143275},
{"learn":[0.6167173445],"iteration":82,"passed_time":1.153796942,"remaining_time":12.74737104},
{"learn":[0.6163866515],"iteration":83,"passed_time":1.166512241,"remaining_time":12.72053825},
{"learn":[0.616068935],"iteration":84,"passed_time":1.180356482,"remaining_time":12.70619036},
{"learn":[0.6156614249],"iteration":85,"passed_time":1.194156481,"remaining_time":12.691384},
{"learn":[0.6153091849],"iteration":86,"passed_time":1.207658645,"remaining_time":12.67347521},
{"learn":[0.6147977258],"iteration":87,"passed_time":1.220650213,"remaining_time":12.65037493},
{"learn":[0.6142023855],"iteration":88,"passed_time":1.235400032,"remaining_time":12.6454992},
{"learn":[0.613712287],"iteration":89,"passed_time":1.249752874,"remaining_time":12.63639017},
{"learn":[0.613251519],"iteration":90,"passed_time":1.263055819,"remaining_time":12.61667846},
{"learn":[0.6129318512],"iteration":91,"passed_time":1.275969247,"remaining_time":12.5932617},
{"learn":[0.6126734777],"iteration":92,"passed_time":1.289252114,"remaining_time":12.57367384},
{"learn":[0.6121540686],"iteration":93,"passed_time":1.30295808,"remaining_time":12.55829809},
{"learn":[0.6118615958],"iteration":94,"passed_time":1.315339098,"remaining_time":12.53033562},
{"learn":[0.6115725565],"iteration":95,"passed_time":1.327509982,"remaining_time":12.50071899},
{"learn":[0.611129302],"iteration":96,"passed_time":1.340379936,"remaining_time":12.47796992},
{"learn":[0.6109005317],"iteration":97,"passed_time":1.352796377,"remaining_time":12.45124829},
{"learn":[0.6105209543],"iteration":98,"passed_time":1.366200182,"remaining_time":12.43380165},
{"learn":[0.6101804773],"iteration":99,"passed_time":1.378539209,"remaining_time":12.40685288},
{"learn":[0.6095692107],"iteration":100,"passed_time":1.392314069,"remaining_time":12.39297374},
{"learn":[0.6091079436],"iteration":101,"passed_time":1.405926761,"remaining_time":12.37766894},
{"learn":[0.6087747162],"iteration":102,"passed_time":1.41946439,"remaining_time":12.36174328},
{"learn":[0.6083519109],"iteration":103,"passed_time":1.432010581,"remaining_time":12.33732193},
{"learn":[0.6078578512],"iteration":104,"passed_time":1.444508793,"remaining_time":12.31271781},
{"learn":[0.6073775272],"iteration":105,"passed_time":1.459621578,"remaining_time":12.31039331},
{"learn":[0.6070042929],"iteration":106,"passed_time":1.472904185,"remaining_time":12.29255549},
{"learn":[0.6066494697],"iteration":107,"passed_time":1.486864704,"remaining_time":12.28040108},
{"learn":[0.6062494385],"iteration":108,"passed_time":1.500589718,"remaining_time":12.26628843},
{"learn":[0.6059029328],"iteration":109,"passed_time":1.512398008,"remaining_time":12.23667479},
{"learn":[0.6055879698],"iteration":110,"passed_time":1.525995771,"remaining_time":12.22171387},
{"learn":[0.6054099576],"iteration":111,"passed_time":1.539291973,"remaining_time":12.20438636},
{"learn":[0.6051348327],"iteration":112,"passed_time":1.552487753,"remaining_time":12.18634192},
{"learn":[0.6045651404],"iteration":113,"passed_time":1.565799725,"remaining_time":12.16928558},
{"learn":[0.6041802898],"iteration":114,"passed_time":1.579280475,"remaining_time":12.15359322},
{"learn":[0.603772383],"iteration":115,"passed_time":1.591221242,"remaining_time":12.12620326},
{"learn":[0.6032975358],"iteration":116,"passed_time":1.604140911,"remaining_time":12.10646517},
{"learn":[0.6027784688],"iteration":117,"passed_time":1.619404663,"remaining_time":12.10436367},
{"learn":[0.6023228943],"iteration":118,"passed_time":1.637624247,"remaining_time":12.12392404},
{"learn":[0.6020455399],"iteration":119,"passed_time":1.656328836,"remaining_time":12.14641147},
{"learn":[0.6017838116],"iteration":120,"passed_time":1.673521421,"remaining_time":12.15723412},
{"learn":[0.6014240448],"iteration":121,"passed_time":1.688874279,"remaining_time":12.15435751},
{"learn":[0.6011480036],"iteration":122,"passed_time":1.703545302,"remaining_time":12.1464165},
{"learn":[0.6007281874],"iteration":123,"passed_time":1.717296008,"remaining_time":12.13186535},
{"learn":[0.6003870883],"iteration":124,"passed_time":1.730939393,"remaining_time":12.11657575},
{"learn":[0.6000247665],"iteration":125,"passed_time":1.74382468,"remaining_time":12.09605373},
{"learn":[0.5996872042],"iteration":126,"passed_time":1.755603808,"remaining_time":12.06804823},
{"learn":[0.5993347666],"iteration":127,"passed_time":1.768164682,"remaining_time":12.04562189},
{"learn":[0.5990704882],"iteration":128,"passed_time":1.781796883,"remaining_time":12.03058205},
{"learn":[0.5985452917],"iteration":129,"passed_time":1.794484517,"remaining_time":12.00924254},
{"learn":[0.5981713308],"iteration":130,"passed_time":1.806739054,"remaining_time":11.98516212},
{"learn":[0.5979272862],"iteration":131,"passed_time":1.818607458,"remaining_time":11.95872177},
{"learn":[0.5975873104],"iteration":132,"passed_time":1.831654094,"remaining_time":11.9401812},
{"learn":[0.5971970123],"iteration":133,"passed_time":1.844291556,"remaining_time":11.91907827},
{"learn":[0.5970833954],"iteration":134,"passed_time":1.857746093,"remaining_time":11.90333608},
{"learn":[0.5968727281],"iteration":135,"passed_time":1.869882601,"remaining_time":11.87925417},
{"learn":[0.5966977727],"iteration":136,"passed_time":1.887069666,"remaining_time":11.88716147},
{"learn":[0.5963310261],"iteration":137,"passed_time":1.903744021,"remaining_time":11.89150251},
{"learn":[0.5960400647],"iteration":138,"passed_time":1.931107964,"remaining_time":11.96175509},
{"learn":[0.59557705],"iteration":139,"passed_time":1.944075443,"remaining_time":11.94217772},
{"learn":[0.5953072759],"iteration":140,"passed_time":1.95676431,"remaining_time":11.92099675},
{"learn":[0.5950732656],"iteration":141,"passed_time":1.969533549,"remaining_time":11.90042102},
{"learn":[0.5949554373],"iteration":142,"passed_time":1.982025368,"remaining_time":11.87829189},
{"learn":[0.5946737558],"iteration":143,"passed_time":1.994163442,"remaining_time":11.85419379},
{"learn":[0.5942451218],"iteration":144,"passed_time":2.007788729,"remaining_time":11.83903009},
{"learn":[0.5937387283],"iteration":145,"passed_time":2.020931924,"remaining_time":11.82106755},
{"learn":[0.593206842],"iteration":146,"passed_time":2.033077342,"remaining_time":11.79738077},
{"learn":[0.5927582391],"iteration":147,"passed_time":2.046954904,"remaining_time":11.78382148},
{"learn":[0.5923210398],"iteration":148,"passed_time":2.060702742,"remaining_time":11.769517},
{"learn":[0.5920304147],"iteration":149,"passed_time":2.074768255,"remaining_time":11.75702011},
{"learn":[0.5917817806],"iteration":150,"passed_time":2.088595782,"remaining_time":11.74316436},
{"learn":[0.5913287169],"iteration":151,"passed_time":2.102490625,"remaining_time":11.72968454},
{"learn":[0.5909426887],"iteration":152,"passed_time":2.114781176,"remaining_time":11.70731801},
{"learn":[0.5905948724],"iteration":153,"passed_time":2.128402524,"remaining_time":11.69239309},
{"learn":[0.5903296985],"iteration":154,"passed_time":2.141362388,"remaining_time":11.67387882},
{"learn":[0.590150477],"iteration":155,"passed_time":2.154191131,"remaining_time":11.65472637},
{"learn":[0.5898564591],"iteration":156,"passed_time":2.167725857,"remaining_time":11.63944521},
{"learn":[0.5894049979],"iteration":157,"passed_time":2.180406739,"remaining_time":11.61963591},
{"learn":[0.5890651865],"iteration":158,"passed_time":2.193523465,"remaining_time":11.6022216},
{"learn":[0.5888436983],"iteration":159,"passed_time":2.207200892,"remaining_time":11.58780468},
{"learn":[0.5886050508],"iteration":160,"passed_time":2.222946385,"remaining_time":11.58417402},
{"learn":[0.5883128198],"iteration":161,"passed_time":2.23712313,"remaining_time":11.57227891},
{"learn":[0.5878302568],"iteration":162,"passed_time":2.252023795,"remaining_time":11.56407311},
{"learn":[0.5875437536],"iteration":163,"passed_time":2.267531786,"remaining_time":11.55888154},
{"learn":[0.5872820483],"iteration":164,"passed_time":2.280147252,"remaining_time":11.538927},
{"learn":[0.5871574178],"iteration":165,"passed_time":2.293950127,"remaining_time":11.52502654},
{"learn":[0.5869304095],"iteration":166,"passed_time":2.309908933,"remaining_time":11.52188108},
{"learn":[0.5865502124],"iteration":167,"passed_time":2.324189906,"remaining_time":11.51027382},
{"learn":[0.5863190265],"iteration":168,"passed_time":2.337730153,"remaining_time":11.49499265},
{"learn":[0.5859913687],"iteration":169,"passed_time":2.351449521,"remaining_time":11.48060649},
{"learn":[0.5855915686],"iteration":170,"passed_time":2.364048692,"remaining_time":11.46079746},
{"learn":[0.5853432147],"iteration":171,"passed_time":2.377254469,"remaining_time":11.44399245},
{"learn":[0.5851013399],"iteration":172,"passed_time":2.392795701,"remaining_time":11.43839332},
{"learn":[0.5846607007],"iteration":173,"passed_time":2.406119989,"remaining_time":11.42215581},
{"learn":[0.5845093003],"iteration":174,"passed_time":2.418483505,"remaining_time":11.40142224},
{"learn":[0.5841619626],"iteration":175,"passed_time":2.431416681,"remaining_time":11.38345083},
{"learn":[0.5839291937],"iteration":176,"passed_time":2.442591737,"remaining_time":11.35736158},
{"learn":[0.5835417544],"iteration":177,"passed_time":2.455021254,"remaining_time":11.33723298},
{"learn":[0.5833606208],"iteration":178,"passed_time":2.467088842,"remaining_time":11.31553039},
{"learn":[0.5829940789],"iteration":179,"passed_time":2.479572931,"remaining_time":11.29583224},
{"learn":[0.5824877648],"iteration":180,"passed_time":2.492219765,"remaining_time":11.27695021},
{"learn":[0.5822175107],"iteration":181,"passed_time":2.504148146,"remaining_time":11.2549076},
{"learn":[0.5818713583],"iteration":182,"passed_time":2.516197582,"remaining_time":11.23351598},
{"learn":[0.5815797722],"iteration":183,"passed_time":2.528186357,"remaining_time":11.21195689},
{"learn":[0.5812283649],"iteration":184,"passed_time":2.539937271,"remaining_time":11.18945338},
{"learn":[0.5810703754],"iteration":185,"passed_time":2.575001279,"remaining_time":11.26909162},
{"learn":[0.58049611],"iteration":186,"passed_time":2.586728664,"remaining_time":11.24604494},
{"learn":[0.5799523251],"iteration":187,"passed_time":2.598670101,"remaining_time":11.2240432},
{"learn":[0.5795670787],"iteration":188,"passed_time":2.609508443,"remaining_time":11.19741454},
{"learn":[0.5793008547],"iteration":189,"passed_time":2.621315455,"remaining_time":11.17508168},
{"learn":[0.5789388631],"iteration":190,"passed_time":2.634626636,"remaining_time":11.1592301},
{"learn":[0.57845374],"iteration":191,"passed_time":2.649411138,"remaining_time":11.1496052},
{"learn":[0.5781130484],"iteration":192,"passed_time":2.662856234,"remaining_time":11.13432632},
{"learn":[0.577727558],"iteration":193,"passed_time":2.67578861,"remaining_time":11.11693618},
{"learn":[0.5772555017],"iteration":194,"passed_time":2.69893557,"remaining_time":11.14175966},
{"learn":[0.5770910072],"iteration":195,"passed_time":2.711181521,"remaining_time":11.12137726},
{"learn":[0.5767245637],"iteration":196,"passed_time":2.722092298,"remaining_time":11.0956351},
{"learn":[0.5764154731],"iteration":197,"passed_time":2.73327309,"remaining_time":11.07113646},
{"learn":[0.5761578324],"iteration":198,"passed_time":2.745666078,"remaining_time":11.0516509},
{"learn":[0.5758414026],"iteration":199,"passed_time":2.75740757,"remaining_time":11.02963028},
{"learn":[0.5754861447],"iteration":200,"passed_time":2.768575326,"remaining_time":11.00543127},
{"learn":[0.5751470977],"iteration":201,"passed_time":2.780543707,"remaining_time":10.98452415},
{"learn":[0.5749059151],"iteration":202,"passed_time":2.793041678,"remaining_time":10.96578432},
{"learn":[0.5746990007],"iteration":203,"passed_time":2.804919788,"remaining_time":10.94468702},
{"learn":[0.5742615254],"iteration":204,"passed_time":2.82216921,"remaining_time":10.94450986},
{"learn":[0.5740076608],"iteration":205,"passed_time":2.833710878,"remaining_time":10.92216717},
{"learn":[0.573581275],"iteration":206,"passed_time":2.845972647,"remaining_time":10.90268748},
{"learn":[0.5731180534],"iteration":207,"passed_time":2.857512141,"remaining_time":10.880527},
{"learn":[0.5726900335],"iteration":208,"passed_time":2.868448963,"remaining_time":10.85618722},
{"learn":[0.5723430793],"iteration":209,"passed_time":2.88049204,"remaining_time":10.83613672},
{"learn":[0.5721766682],"iteration":210,"passed_time":2.893650729,"remaining_time":10.82033377},
{"learn":[0.5718859646],"iteration":211,"passed_time":2.906439886,"remaining_time":10.80318222},
{"learn":[0.5715282786],"iteration":212,"passed_time":2.934487835,"remaining_time":10.84245036},
{"learn":[0.5712243194],"iteration":213,"passed_time":2.945078578,"remaining_time":10.81697085},
{"learn":[0.5709819075],"iteration":214,"passed_time":2.956630576,"remaining_time":10.79513955},
{"learn":[0.5705645888],"iteration":215,"passed_time":2.967924993,"remaining_time":10.77246849},
{"learn":[0.5702699907],"iteration":216,"passed_time":2.979325051,"remaining_time":10.75028348},
{"learn":[0.5698396914],"iteration":217,"passed_time":2.991807553,"remaining_time":10.73208031},
{"learn":[0.5694769795],"iteration":218,"passed_time":3.003888868,"remaining_time":10.71249866},
{"learn":[0.5693271058],"iteration":219,"passed_time":3.015920231,"remaining_time":10.69280809},
{"learn":[0.5690184973],"iteration":220,"passed_time":3.02762704,"remaining_time":10.67204282},
{"learn":[0.5687819791],"iteration":221,"passed_time":3.040909556,"remaining_time":10.65688124},
{"learn":[0.568459476],"iteration":222,"passed_time":3.053601165,"remaining_time":10.6396776},
{"learn":[0.5680973324],"iteration":223,"passed_time":3.065608173,"remaining_time":10.6201426},
{"learn":[0.567803606],"iteration":224,"passed_time":3.077639702,"remaining_time":10.60075897},
{"learn":[0.567575772],"iteration":225,"passed_time":3.107126074,"remaining_time":10.64121939},
{"learn":[0.5673532974],"iteration":226,"passed_time":3.119329554,"remaining_time":10.62221033},
{"learn":[0.5671580483],"iteration":227,"passed_time":3.131499277,"remaining_time":10.60314667},
{"learn":[0.5668639415],"iteration":228,"passed_time":3.143334258,"remaining_time":10.58301621},
{"learn":[0.5664674226],"iteration":229,"passed_time":3.156166726,"remaining_time":10.5662973},
{"learn":[0.5663438447],"iteration":230,"passed_time":3.168865574,"remaining_time":10.54916721},
{"learn":[0.5662679993],"iteration":231,"passed_time":3.181626835,"remaining_time":10.53228194},
{"learn":[0.5659324509],"iteration":232,"passed_time":3.193565679,"remaining_time":10.51272479},
{"learn":[0.5653964429],"iteration":233,"passed_time":3.207103909,"remaining_time":10.49846835},
{"learn":[0.5651781442],"iteration":234,"passed_time":3.220045185,"remaining_time":10.48227475},
{"learn":[0.564886005],"iteration":235,"passed_time":3.232598866,"remaining_time":10.46485396},
{"learn":[0.5644477969],"iteration":236,"passed_time":3.246412224,"remaining_time":10.45152965},
{"learn":[0.5641052148],"iteration":237,"passed_time":3.258868875,"remaining_time":10.43385749},
{"learn":[0.5635820569],"iteration":238,"passed_time":3.273121693,"remaining_time":10.42194815},
{"learn":[0.563327141],"iteration":239,"passed_time":3.288058332,"remaining_time":10.41218472},
{"learn":[0.5629868751],"iteration":240,"passed_time":3.302509654,"remaining_time":10.40084991},
{"learn":[0.5626391058],"iteration":241,"passed_time":3.316453494,"remaining_time":10.38789979},
{"learn":[0.5624082053],"iteration":242,"passed_time":3.328940591,"remaining_time":10.37040341},
{"learn":[0.5620549789],"iteration":243,"passed_time":3.340990603,"remaining_time":10.35159384},
{"learn":[0.5618268532],"iteration":244,"passed_time":3.3531192,"remaining_time":10.33308162},
{"learn":[0.5615019058],"iteration":245,"passed_time":3.365211653,"remaining_time":10.31451051},
{"learn":[0.5612679529],"iteration":246,"passed_time":3.377325913,"remaining_time":10.29605835},
{"learn":[0.5610801494],"iteration":247,"passed_time":3.388692013,"remaining_time":10.27538869},
{"learn":[0.560824478],"iteration":248,"passed_time":3.400871523,"remaining_time":10.25724704},
{"learn":[0.5605641587],"iteration":249,"passed_time":3.413252342,"remaining_time":10.23975702},
{"learn":[0.5602255489],"iteration":250,"passed_time":3.425375607,"remaining_time":10.22153916},
{"learn":[0.5600825467],"iteration":251,"passed_time":3.436535664,"remaining_time":10.20051062},
{"learn":[0.559814316],"iteration":252,"passed_time":3.448520405,"remaining_time":10.18199503},
{"learn":[0.5593444854],"iteration":253,"passed_time":3.461750196,"remaining_time":10.16718758},
{"learn":[0.5590336621],"iteration":254,"passed_time":3.474004939,"remaining_time":10.14954384},
{"learn":[0.5587719325],"iteration":255,"passed_time":3.49301203,"remaining_time":10.15156621},
{"learn":[0.5585556572],"iteration":256,"passed_time":3.504293898,"remaining_time":10.13109092},
{"learn":[0.5581541465],"iteration":257,"passed_time":3.516970128,"remaining_time":10.11469704},
{"learn":[0.5578845295],"iteration":258,"passed_time":3.529869272,"remaining_time":10.09896962},
{"learn":[0.557674652],"iteration":259,"passed_time":3.542246541,"remaining_time":10.08177862},
{"learn":[0.5573742184],"iteration":260,"passed_time":3.553449065,"remaining_time":10.06129831},
{"learn":[0.5572167651],"iteration":261,"passed_time":3.565529844,"remaining_time":10.04336269},
{"learn":[0.5569966905],"iteration":262,"passed_time":3.577708112,"remaining_time":10.02574478},
{"learn":[0.5567641014],"iteration":263,"passed_time":3.588913815,"remaining_time":10.0054567},
{"learn":[0.5565784753],"iteration":264,"passed_time":3.600648854,"remaining_time":9.986705313},
{"learn":[0.5562207619],"iteration":265,"passed_time":3.616833291,"remaining_time":9.980284346},
{"learn":[0.5560489732],"iteration":266,"passed_time":3.629123018,"remaining_time":9.963098022},
{"learn":[0.5558608867],"iteration":267,"passed_time":3.641372533,"remaining_time":9.945838412},
{"learn":[0.5556581164],"iteration":268,"passed_time":3.652386581,"remaining_time":9.925258701},
{"learn":[0.555334959],"iteration":269,"passed_time":3.663968537,"remaining_time":9.906285303},
{"learn":[0.5550482266],"iteration":270,"passed_time":3.676041066,"remaining_time":9.888686114},
{"learn":[0.5547670853],"iteration":271,"passed_time":3.688323262,"remaining_time":9.87168873},
{"learn":[0.5546181757],"iteration":272,"passed_time":3.699568143,"remaining_time":9.851963516},
{"learn":[0.5542956187],"iteration":273,"passed_time":3.724586714,"remaining_time":9.868795454},
{"learn":[0.5540891574],"iteration":274,"passed_time":3.73616491,"remaining_time":9.849889308},
{"learn":[0.5539143187],"iteration":275,"passed_time":3.747054744,"remaining_time":9.829230561},
{"learn":[0.5538508739],"iteration":276,"passed_time":3.758795115,"remaining_time":9.810862339},
{"learn":[0.5534334848],"iteration":277,"passed_time":3.770141331,"remaining_time":9.791518134},
{"learn":[0.5531930759],"iteration":278,"passed_time":3.781613031,"remaining_time":9.772555539},
{"learn":[0.5528944956],"iteration":279,"passed_time":3.794281532,"remaining_time":9.75672394},
{"learn":[0.5528092698],"iteration":280,"passed_time":3.805713384,"remaining_time":9.737750615},
{"learn":[0.5523560102],"iteration":281,"passed_time":3.816976838,"remaining_time":9.71840202},
{"learn":[0.5521492962],"iteration":282,"passed_time":3.829109676,"remaining_time":9.701313208},
{"learn":[0.5518265498],"iteration":283,"passed_time":3.841141705,"remaining_time":9.684005144},
{"learn":[0.5515421018],"iteration":284,"passed_time":3.853845945,"remaining_time":9.668420528},
{"learn":[0.5512266309],"iteration":285,"passed_time":3.878811766,"remaining_time":9.683467137},
{"learn":[0.5509303441],"iteration":286,"passed_time":3.890628813,"remaining_time":9.665569142},
{"learn":[0.5506125598],"iteration":287,"passed_time":3.902395203,"remaining_time":9.647588142},
{"learn":[0.5503227074],"iteration":288,"passed_time":3.913499292,"remaining_time":9.628020749},
{"learn":[0.5500519435],"iteration":289,"passed_time":3.925713564,"remaining_time":9.61122976},
{"learn":[0.5497417244],"iteration":290,"passed_time":3.938122617,"remaining_time":9.594944795},
{"learn":[0.5495244785],"iteration":291,"passed_time":3.950828664,"remaining_time":9.579406486},
{"learn":[0.5493868549],"iteration":292,"passed_time":3.961682054,"remaining_time":9.559417106},
{"learn":[0.5490170102],"iteration":293,"passed_time":3.973678765,"remaining_time":9.542235401},
{"learn":[0.5487195264],"iteration":294,"passed_time":3.98589121,"remaining_time":9.525604418},
{"learn":[0.5484164098],"iteration":295,"passed_time":3.997120403,"remaining_time":9.506664741},
{"learn":[0.5481018051],"iteration":296,"passed_time":4.008641723,"remaining_time":9.488468456},
{"learn":[0.5475317816],"iteration":297,"passed_time":4.022140746,"remaining_time":9.474975851},
{"learn":[0.547244973],"iteration":298,"passed_time":4.03455973,"remaining_time":9.458951072},
{"learn":[0.5469655172],"iteration":299,"passed_time":4.047076795,"remaining_time":9.443179189},
{"learn":[0.5465726626],"iteration":300,"passed_time":4.059245312,"remaining_time":9.426619512},
{"learn":[0.5463262402],"iteration":301,"passed_time":4.07129289,"remaining_time":9.409809394},
{"learn":[0.5460251746],"iteration":302,"passed_time":4.084167173,"remaining_time":9.394932409},
{"learn":[0.5456677576],"iteration":303,"passed_time":4.096626227,"remaining_time":9.379117941},
{"learn":[0.5454192185],"iteration":304,"passed_time":4.108535405,"remaining_time":9.36207248},
{"learn":[0.5451006587],"iteration":305,"passed_time":4.12243951,"remaining_time":9.349585033},
{"learn":[0.5448185246],"iteration":306,"passed_time":4.137382908,"remaining_time":9.339434381},
{"learn":[0.5445888005],"iteration":307,"passed_time":4.149952467,"remaining_time":9.32391918},
{"learn":[0.544172299],"iteration":308,"passed_time":4.162422889,"remaining_time":9.308201348},
{"learn":[0.5439922613],"iteration":309,"passed_time":4.174172026,"remaining_time":9.290899026},
{"learn":[0.5435937565],"iteration":310,"passed_time":4.187244593,"remaining_time":9.276564389},
{"learn":[0.5431871571],"iteration":311,"passed_time":4.20012437,"remaining_time":9.261812713},
{"learn":[0.5428959902],"iteration":312,"passed_time":4.217312481,"remaining_time":9.256529312},
{"learn":[0.5424422061],"iteration":313,"passed_time":4.230006678,"remaining_time":9.24135217},
{"learn":[0.5422721785],"iteration":314,"passed_time":4.24180043,"remaining_time":9.224232681},
{"learn":[0.5419658578],"iteration":315,"passed_time":4.254865578,"remaining_time":9.20989891},
{"learn":[0.5415283381],"iteration":316,"passed_time":4.268376866,"remaining_time":9.196534383},
{"learn":[0.5413609682],"iteration":317,"passed_time":4.282299187,"remaining_time":9.184050459},
{"learn":[0.5412141375],"iteration":318,"passed_time":4.29553864,"remaining_time":9.170099731},
{"learn":[0.5409206251],"iteration":319,"passed_time":4.307040052,"remaining_time":9.152460111},
{"learn":[0.54045254],"iteration":320,"passed_time":4.31853008,"remaining_time":9.134834656},
{"learn":[0.5401410487],"iteration":321,"passed_time":4.330923023,"remaining_time":9.119148477},
{"learn":[0.5398578782],"iteration":322,"passed_time":4.343599779,"remaining_time":9.104077554},
{"learn":[0.5395880073],"iteration":323,"passed_time":4.355518498,"remaining_time":9.08743983},
{"learn":[0.5394538702],"iteration":324,"passed_time":4.379848598,"remaining_time":9.096608626},
{"learn":[0.539061664],"iteration":325,"passed_time":4.390389704,"remaining_time":9.077063376},
{"learn":[0.5387158862],"iteration":326,"passed_time":4.40110517,"remaining_time":9.057932047},
{"learn":[0.5383457362],"iteration":327,"passed_time":4.412790167,"remaining_time":9.040838391},
{"learn":[0.5380399286],"iteration":328,"passed_time":4.424462674,"remaining_time":9.02375214},
{"learn":[0.5378117667],"iteration":329,"passed_time":4.435509863,"remaining_time":9.005429115},
{"learn":[0.537367134],"iteration":330,"passed_time":4.447765446,"remaining_time":8.989592396},
{"learn":[0.537098093],"iteration":331,"passed_time":4.46025668,"remaining_time":8.974251391},
{"learn":[0.5367723053],"iteration":332,"passed_time":4.471910593,"remaining_time":8.957250347},
{"learn":[0.536473701],"iteration":333,"passed_time":4.484652225,"remaining_time":8.942450244},
{"learn":[0.5361442597],"iteration":334,"passed_time":4.497541577,"remaining_time":8.927955667},
{"learn":[0.5358034417],"iteration":335,"passed_time":4.509938664,"remaining_time":8.912497837},
{"learn":[0.5355664008],"iteration":336,"passed_time":4.522722282,"remaining_time":8.897818614},
{"learn":[0.5353599959],"iteration":337,"passed_time":4.534156472,"remaining_time":8.880507646},
{"learn":[0.5350496522],"iteration":338,"passed_time":4.546869097,"remaining_time":8.86572411},
{"learn":[0.5348094694],"iteration":339,"passed_time":4.559400319,"remaining_time":8.850600619},
{"learn":[0.5346263245],"iteration":340,"passed_time":4.571149725,"remaining_time":8.833981434},
{"learn":[0.53443722],"iteration":341,"passed_time":4.582390271,"remaining_time":8.816411692},
{"learn":[0.5341288111],"iteration":342,"passed_time":4.594796135,"remaining_time":8.801110964},
{"learn":[0.5338511225],"iteration":343,"passed_time":4.608032234,"remaining_time":8.787410306},
{"learn":[0.5334822236],"iteration":344,"passed_time":4.621194883,"remaining_time":8.773572893},
{"learn":[0.5333086512],"iteration":345,"passed_time":4.633382848,"remaining_time":8.757897059},
{"learn":[0.5331652019],"iteration":346,"passed_time":4.645551474,"remaining_time":8.742204936},
{"learn":[0.5328849019],"iteration":347,"passed_time":4.657960051,"remaining_time":8.726982625},
{"learn":[0.5327949719],"iteration":348,"passed_time":4.670310594,"remaining_time":8.711668186},
{"learn":[0.5323900712],"iteration":349,"passed_time":4.682300772,"remaining_time":8.695701433},
{"learn":[0.5321258517],"iteration":350,"passed_time":4.694471759,"remaining_time":8.680091656},
{"learn":[0.5319881449],"iteration":351,"passed_time":4.706386413,"remaining_time":8.664029534},
{"learn":[0.531764481],"iteration":352,"passed_time":4.717947714,"remaining_time":8.647343261},
{"learn":[0.5316429319],"iteration":353,"passed_time":4.729068143,"remaining_time":8.629881413},
{"learn":[0.5312650569],"iteration":354,"passed_time":4.741186477,"remaining_time":8.614268389},
{"learn":[0.530893263],"iteration":355,"passed_time":4.753733609,"remaining_time":8.599450686},
{"learn":[0.5307639616],"iteration":356,"passed_time":4.765122748,"remaining_time":8.582560019},
{"learn":[0.530546411],"iteration":357,"passed_time":4.778281111,"remaining_time":8.568872831},
{"learn":[0.5303234221],"iteration":358,"passed_time":4.790684191,"remaining_time":8.553840018},
{"learn":[0.5298852026],"iteration":359,"passed_time":4.8032573,"remaining_time":8.539124088},
{"learn":[0.5296076504],"iteration":360,"passed_time":4.815047521,"remaining_time":8.523034255},
{"learn":[0.5293172011],"iteration":361,"passed_time":4.82719745,"remaining_time":8.507602136},
{"learn":[0.5290882107],"iteration":362,"passed_time":4.839620535,"remaining_time":8.492667441},
{"learn":[0.5290149985],"iteration":363,"passed_time":4.852061031,"remaining_time":8.477776966},
{"learn":[0.5288365513],"iteration":364,"passed_time":4.863456833,"remaining_time":8.461082436},
{"learn":[0.5286572946],"iteration":365,"passed_time":4.886809536,"remaining_time":8.465129087},
{"learn":[0.5281944958],"iteration":366,"passed_time":4.898217488,"remaining_time":8.448424168},
{"learn":[0.5279369305],"iteration":367,"passed_time":4.909531414,"remaining_time":8.431586559},
{"learn":[0.5277559916],"iteration":368,"passed_time":4.921195761,"remaining_time":8.415378117},
{"learn":[0.5274680254],"iteration":369,"passed_time":4.965752347,"remaining_time":8.455199941},
{"learn":[0.5271818468],"iteration":370,"passed_time":4.977968241,"remaining_time":8.439735913},
{"learn":[0.5270363619],"iteration":371,"passed_time":4.989385324,"remaining_time":8.422940816},
{"learn":[0.5267175992],"iteration":372,"passed_time":5.001351795,"remaining_time":8.407098058},
{"learn":[0.5263437779],"iteration":373,"passed_time":5.012376604,"remaining_time":8.389699877},
{"learn":[0.5261076889],"iteration":374,"passed_time":5.024073751,"remaining_time":8.373456252},
{"learn":[0.5257741959],"iteration":375,"passed_time":5.036989846,"remaining_time":8.359259745},
{"learn":[0.5255656985],"iteration":376,"passed_time":5.049922002,"remaining_time":8.34509657},
{"learn":[0.5251773892],"iteration":377,"passed_time":5.06093637,"remaining_time":8.327784185},
{"learn":[0.5249382631],"iteration":378,"passed_time":5.073044522,"remaining_time":8.312297225},
{"learn":[0.5246310314],"iteration":379,"passed_time":5.086298606,"remaining_time":8.298697725},
{"learn":[0.5244606836],"iteration":380,"passed_time":5.098789727,"remaining_time":8.283860475},
{"learn":[0.5241043595],"iteration":381,"passed_time":5.112814229,"remaining_time":8.271516213},
{"learn":[0.5239066971],"iteration":382,"passed_time":5.124252494,"remaining_time":8.254996837},
{"learn":[0.523699892],"iteration":383,"passed_time":5.136178332,"remaining_time":8.239286074},
{"learn":[0.5234686947],"iteration":384,"passed_time":5.14888534,"remaining_time":8.224842816},
{"learn":[0.5231564706],"iteration":385,"passed_time":5.162461832,"remaining_time":8.211791619},
{"learn":[0.5230043325],"iteration":386,"passed_time":5.175051792,"remaining_time":8.197175061},
{"learn":[0.5228221642],"iteration":387,"passed_time":5.188248192,"remaining_time":8.183525499},
{"learn":[0.5226145755],"iteration":388,"passed_time":5.201039354,"remaining_time":8.169241761},
{"learn":[0.5225006702],"iteration":389,"passed_time":5.214179339,"remaining_time":8.155511274},
{"learn":[0.5222466424],"iteration":390,"passed_time":5.226792432,"remaining_time":8.140963149},
{"learn":[0.5217599692],"iteration":391,"passed_time":5.239507416,"remaining_time":8.126582931},
{"learn":[0.5215186801],"iteration":392,"passed_time":5.25284475,"remaining_time":8.113172425},
{"learn":[0.5211965195],"iteration":393,"passed_time":5.266938803,"remaining_time":8.100926179},
{"learn":[0.5210251121],"iteration":394,"passed_time":5.280126262,"remaining_time":8.087281996},
{"learn":[0.5207778054],"iteration":395,"passed_time":5.292845375,"remaining_time":8.072925774},
{"learn":[0.5203299577],"iteration":396,"passed_time":5.305720625,"remaining_time":8.058814955},
{"learn":[0.5199728963],"iteration":397,"passed_time":5.317901512,"remaining_time":8.043660076},
{"learn":[0.5198317871],"iteration":398,"passed_time":5.330067266,"remaining_time":8.02849731},
{"learn":[0.5195292537],"iteration":399,"passed_time":5.341873287,"remaining_time":8.01280993},
{"learn":[0.519418281],"iteration":400,"passed_time":5.353090734,"remaining_time":7.996262718},
{"learn":[0.519087003],"iteration":401,"passed_time":5.36485982,"remaining_time":7.980562617},
{"learn":[0.5186492876],"iteration":402,"passed_time":5.377993643,"remaining_time":7.966903734},
{"learn":[0.5183752553],"iteration":403,"passed_time":5.390204632,"remaining_time":7.951886041},
{"learn":[0.5179889236],"iteration":404,"passed_time":5.402353269,"remaining_time":7.936790606},
{"learn":[0.517675824],"iteration":405,"passed_time":5.420513245,"remaining_time":7.930504599},
{"learn":[0.5175399016],"iteration":406,"passed_time":5.431429245,"remaining_time":7.913605754},
{"learn":[0.5172762912],"iteration":407,"passed_time":5.443313099,"remaining_time":7.898140574},
{"learn":[0.5170845361],"iteration":408,"passed_time":5.453780234,"remaining_time":7.880645766},
{"learn":[0.5167888602],"iteration":409,"passed_time":5.468609441,"remaining_time":7.869462366},
{"learn":[0.5166342946],"iteration":410,"passed_time":5.481225028,"remaining_time":7.855088908},
{"learn":[0.516462087],"iteration":411,"passed_time":5.493065811,"remaining_time":7.839618196},
{"learn":[0.5162412996],"iteration":412,"passed_time":5.504090602,"remaining_time":7.823005287},
{"learn":[0.5160234765],"iteration":413,"passed_time":5.516768227,"remaining_time":7.808758891},
{"learn":[0.5157986366],"iteration":414,"passed_time":5.529364662,"remaining_time":7.794405608},
{"learn":[0.5155139626],"iteration":415,"passed_time":5.541404466,"remaining_time":7.779279346},
{"learn":[0.5152934961],"iteration":416,"passed_time":5.552877808,"remaining_time":7.763375928},
{"learn":[0.514981295],"iteration":417,"passed_time":5.579232987,"remaining_time":7.76821435},
{"learn":[0.5146257428],"iteration":418,"passed_time":5.590631636,"remaining_time":7.752164632},
{"learn":[0.5144050529],"iteration":419,"passed_time":5.601522292,"remaining_time":7.735435547},
{"learn":[0.5141063108],"iteration":420,"passed_time":5.613449568,"remaining_time":7.720159857},
{"learn":[0.5137923437],"iteration":421,"passed_time":5.639104541,"remaining_time":7.723702429},
{"learn":[0.5136430234],"iteration":422,"passed_time":5.65005106,"remaining_time":7.707043645},
{"learn":[0.5131515134],"iteration":423,"passed_time":5.671567302,"remaining_time":7.704770674},
{"learn":[0.5129413253],"iteration":424,"passed_time":5.682092318,"remaining_time":7.687536666},
{"learn":[0.5125829753],"iteration":425,"passed_time":5.69433441,"remaining_time":7.672647773},
{"learn":[0.5123688321],"iteration":426,"passed_time":5.705949001,"remaining_time":7.656929221},
{"learn":[0.5120431367],"iteration":427,"passed_time":5.717589029,"remaining_time":7.641263842},
{"learn":[0.5119239132],"iteration":428,"passed_time":5.729855825,"remaining_time":7.62645146},
{"learn":[0.5114891921],"iteration":429,"passed_time":5.741737893,"remaining_time":7.611140928},
{"learn":[0.5112521595],"iteration":430,"passed_time":5.753871414,"remaining_time":7.59617827},
{"learn":[0.5110180377],"iteration":431,"passed_time":5.7659496,"remaining_time":7.581155955},
{"learn":[0.5107446333],"iteration":432,"passed_time":5.77754379,"remaining_time":7.565513462},
{"learn":[0.510301517],"iteration":433,"passed_time":5.79027581,"remaining_time":7.551373521},
{"learn":[0.509948894],"iteration":434,"passed_time":5.80287831,"remaining_time":7.537071828},
{"learn":[0.5096336372],"iteration":435,"passed_time":5.814037,"remaining_time":7.520910247},
{"learn":[0.5092772073],"iteration":436,"passed_time":5.826153688,"remaining_time":7.506005781},
{"learn":[0.5089724565],"iteration":437,"passed_time":5.839147336,"remaining_time":7.492239276},
{"learn":[0.5087544289],"iteration":438,"passed_time":5.850820071,"remaining_time":7.476788291},
{"learn":[0.5084962259],"iteration":439,"passed_time":5.861776978,"remaining_time":7.460443427},
{"learn":[0.5081864215],"iteration":440,"passed_time":5.874806333,"remaining_time":7.446749978},
{"learn":[0.508008248],"iteration":441,"passed_time":5.886769037,"remaining_time":7.431712947},
{"learn":[0.5074681633],"iteration":442,"passed_time":5.898278183,"remaining_time":7.416119522},
{"learn":[0.5070035466],"iteration":443,"passed_time":5.910026356,"remaining_time":7.400843815},
{"learn":[0.5066845021],"iteration":444,"passed_time":5.921814087,"remaining_time":7.3856333},
{"learn":[0.5064050885],"iteration":445,"passed_time":5.934010663,"remaining_time":7.370945981},
{"learn":[0.5061712523],"iteration":446,"passed_time":5.945532385,"remaining_time":7.355434919},
{"learn":[0.5058311122],"iteration":447,"passed_time":5.957080789,"remaining_time":7.339974544},
{"learn":[0.5055178977],"iteration":448,"passed_time":5.969131731,"remaining_time":7.325148294},
{"learn":[0.5050764705],"iteration":449,"passed_time":5.982410468,"remaining_time":7.311835016},
{"learn":[0.5048607139],"iteration":450,"passed_time":5.99364155,"remaining_time":7.296029292},
{"learn":[0.5046660731],"iteration":451,"passed_time":6.005419163,"remaining_time":7.280906419},
{"learn":[0.5043327263],"iteration":452,"passed_time":6.018275715,"remaining_time":7.26710114},
{"learn":[0.5040386997],"iteration":453,"passed_time":6.029859263,"remaining_time":7.251769069},
{"learn":[0.5037919347],"iteration":454,"passed_time":6.041872409,"remaining_time":7.23696805},
{"learn":[0.5034097652],"iteration":455,"passed_time":6.055089675,"remaining_time":7.223615752},
{"learn":[0.5031995013],"iteration":456,"passed_time":6.067392296,"remaining_time":7.209177279},
{"learn":[0.5028718223],"iteration":457,"passed_time":6.079092226,"remaining_time":7.194034905},
{"learn":[0.5025971966],"iteration":458,"passed_time":6.092085046,"remaining_time":7.180431394},
{"learn":[0.5023768534],"iteration":459,"passed_time":6.105918179,"remaining_time":7.167816993},
{"learn":[0.5021351746],"iteration":460,"passed_time":6.119328502,"remaining_time":7.154702955},
{"learn":[0.5019746271],"iteration":461,"passed_time":6.134484601,"remaining_time":7.143620596},
{"learn":[0.5018418689],"iteration":462,"passed_time":6.14737166,"remaining_time":7.129888945},
{"learn":[0.5015808722],"iteration":463,"passed_time":6.161455096,"remaining_time":7.117542955},
{"learn":[0.5012547777],"iteration":464,"passed_time":6.174078217,"remaining_time":7.103509346},
{"learn":[0.5009783073],"iteration":465,"passed_time":6.187061584,"remaining_time":7.089894605},
{"learn":[0.5007638665],"iteration":466,"passed_time":6.200450531,"remaining_time":7.076745467},
{"learn":[0.5005222897],"iteration":467,"passed_time":6.214008545,"remaining_time":7.063787492},
{"learn":[0.500226727],"iteration":468,"passed_time":6.227043948,"remaining_time":7.050235258},
{"learn":[0.4999896632],"iteration":469,"passed_time":6.239714091,"remaining_time":7.036273337},
{"learn":[0.4997971867],"iteration":470,"passed_time":6.251436189,"remaining_time":7.02125211},
{"learn":[0.4995207613],"iteration":471,"passed_time":6.263760397,"remaining_time":7.00691841},
{"learn":[0.4993134555],"iteration":472,"passed_time":6.282980791,"remaining_time":7.000276695},
{"learn":[0.499083694],"iteration":473,"passed_time":6.309526269,"remaining_time":7.001710585},
{"learn":[0.4987411968],"iteration":474,"passed_time":6.319515096,"remaining_time":6.984727212},
{"learn":[0.4986641605],"iteration":475,"passed_time":6.331781353,"remaining_time":6.970280314},
{"learn":[0.4984570025],"iteration":476,"passed_time":6.343415022,"remaining_time":6.955148966},
{"learn":[0.4980916361],"iteration":477,"passed_time":6.354856725,"remaining_time":6.939822617},
{"learn":[0.497766257],"iteration":478,"passed_time":6.375079887,"remaining_time":6.934063927},
{"learn":[0.4972278835],"iteration":479,"passed_time":6.38595187,"remaining_time":6.918114526},
{"learn":[0.4967914048],"iteration":480,"passed_time":6.398262297,"remaining_time":6.90373832},
{"learn":[0.4964725966],"iteration":481,"passed_time":6.409856097,"remaining_time":6.888600535},
{"learn":[0.4960289179],"iteration":482,"passed_time":6.421451239,"remaining_time":6.873478862},
{"learn":[0.4956662755],"iteration":483,"passed_time":6.432916321,"remaining_time":6.858233103},
{"learn":[0.4955006951],"iteration":484,"passed_time":6.445528027,"remaining_time":6.844220483},
{"learn":[0.4952350412],"iteration":485,"passed_time":6.457178482,"remaining_time":6.829196995},
{"learn":[0.494851089],"iteration":486,"passed_time":6.46881888,"remaining_time":6.814176767},
{"learn":[0.4945714651],"iteration":487,"passed_time":6.482506043,"remaining_time":6.801317816},
{"learn":[0.4943670511],"iteration":488,"passed_time":6.494937217,"remaining_time":6.787142982},
{"learn":[0.4940348465],"iteration":489,"passed_time":6.506640927,"remaining_time":6.772218108},
{"learn":[0.4938183222],"iteration":490,"passed_time":6.517660612,"remaining_time":6.756597253},
{"learn":[0.493470584],"iteration":491,"passed_time":6.529940465,"remaining_time":6.742296253},
{"learn":[0.4932428336],"iteration":492,"passed_time":6.54236742,"remaining_time":6.72815473},
{"learn":[0.4929720437],"iteration":493,"passed_time":6.570396766,"remaining_time":6.730001546},
{"learn":[0.4926535429],"iteration":494,"passed_time":6.581025816,"remaining_time":6.713975833},
{"learn":[0.4922430807],"iteration":495,"passed_time":6.592753616,"remaining_time":6.699088352},
{"learn":[0.4919960261],"iteration":496,"passed_time":6.615287543,"remaining_time":6.695150169},
{"learn":[0.4916029983],"iteration":497,"passed_time":6.626350826,"remaining_time":6.679574528},
{"learn":[0.4914429082],"iteration":498,"passed_time":6.638753055,"remaining_time":6.665361284},
{"learn":[0.4911647389],"iteration":499,"passed_time":6.650900421,"remaining_time":6.650900421},
{"learn":[0.4907743268],"iteration":500,"passed_time":6.682836354,"remaining_time":6.656158365},
{"learn":[0.4904672787],"iteration":501,"passed_time":6.694999524,"remaining_time":6.641652914},
{"learn":[0.4900035756],"iteration":502,"passed_time":6.708852837,"remaining_time":6.628826759},
{"learn":[0.4896659757],"iteration":503,"passed_time":6.720913996,"remaining_time":6.614232822},
{"learn":[0.4893648682],"iteration":504,"passed_time":6.732785838,"remaining_time":6.599463346},
{"learn":[0.4889395652],"iteration":505,"passed_time":6.745102157,"remaining_time":6.58513926},
{"learn":[0.4886609973],"iteration":506,"passed_time":6.757193988,"remaining_time":6.570604805},
{"learn":[0.4884477375],"iteration":507,"passed_time":6.771009584,"remaining_time":6.55774944},
{"learn":[0.4881065109],"iteration":508,"passed_time":6.784657815,"remaining_time":6.544728855},
{"learn":[0.4878686442],"iteration":509,"passed_time":6.796134331,"remaining_time":6.529619259},
{"learn":[0.487538411],"iteration":510,"passed_time":6.823599264,"remaining_time":6.529823953},
{"learn":[0.4872374912],"iteration":511,"passed_time":6.8352834,"remaining_time":6.514879491},
{"learn":[0.4869725236],"iteration":512,"passed_time":6.846952588,"remaining_time":6.499933548},
{"learn":[0.4865232345],"iteration":513,"passed_time":6.860466436,"remaining_time":6.486744529},
{"learn":[0.486083242],"iteration":514,"passed_time":6.874611132,"remaining_time":6.474148347},
{"learn":[0.4855688122],"iteration":515,"passed_time":6.888910004,"remaining_time":6.461690779},
{"learn":[0.4851987923],"iteration":516,"passed_time":6.903392926,"remaining_time":6.449398033},
{"learn":[0.4849525508],"iteration":517,"passed_time":6.917076464,"remaining_time":6.436353003},
{"learn":[0.4846543186],"iteration":518,"passed_time":6.929530607,"remaining_time":6.422166131},
{"learn":[0.4843514998],"iteration":519,"passed_time":6.94198893,"remaining_time":6.407989781},
{"learn":[0.4841567418],"iteration":520,"passed_time":6.955346859,"remaining_time":6.394647112},
{"learn":[0.483944821],"iteration":521,"passed_time":6.967852174,"remaining_time":6.380523638},
{"learn":[0.4835865296],"iteration":522,"passed_time":6.979715616,"remaining_time":6.365820935},
{"learn":[0.4831780338],"iteration":523,"passed_time":6.9915163,"remaining_time":6.351072059},
{"learn":[0.4827590298],"iteration":524,"passed_time":7.005362679,"remaining_time":6.338185281},
{"learn":[0.4824009679],"iteration":525,"passed_time":7.017156686,"remaining_time":6.323445378},
{"learn":[0.4822997025],"iteration":526,"passed_time":7.028863345,"remaining_time":6.308638258},
{"learn":[0.4819148131],"iteration":527,"passed_time":7.041035638,"remaining_time":6.294259131},
{"learn":[0.4815129591],"iteration":528,"passed_time":7.0539347,"remaining_time":6.280535433},
{"learn":[0.4811277774],"iteration":529,"passed_time":7.067115213,"remaining_time":6.267064434},
{"learn":[0.480867176],"iteration":530,"passed_time":7.080241159,"remaining_time":6.253546334},
{"learn":[0.4806486826],"iteration":531,"passed_time":7.091922637,"remaining_time":6.238759012},
{"learn":[0.4802859917],"iteration":532,"passed_time":7.11406698,"remaining_time":6.233150619},
{"learn":[0.4799377845],"iteration":533,"passed_time":7.12569089,"remaining_time":6.218299541},
{"learn":[0.4796796093],"iteration":534,"passed_time":7.137783491,"remaining_time":6.203867894},
{"learn":[0.4793518826],"iteration":535,"passed_time":7.150809721,"remaining_time":6.190253192},
{"learn":[0.4790278542],"iteration":536,"passed_time":7.16302026,"remaining_time":6.175937393},
{"learn":[0.4784597427],"iteration":537,"passed_time":7.176394208,"remaining_time":6.162628483},
{"learn":[0.4780907094],"iteration":538,"passed_time":7.190336164,"remaining_time":6.149805142},
{"learn":[0.4777589543],"iteration":539,"passed_time":7.202645324,"remaining_time":6.135586758},
{"learn":[0.4773526301],"iteration":540,"passed_time":7.215954583,"remaining_time":6.122223944},
{"learn":[0.4768523565],"iteration":541,"passed_time":7.229451418,"remaining_time":6.109019833},
{"learn":[0.4764329014],"iteration":542,"passed_time":7.242633966,"remaining_time":6.095550133},
{"learn":[0.4760465234],"iteration":543,"passed_time":7.254350937,"remaining_time":6.080852991},
{"learn":[0.4758946939],"iteration":544,"passed_time":7.266327788,"remaining_time":6.06638375},
{"learn":[0.4754534105],"iteration":545,"passed_time":7.279260875,"remaining_time":6.052718749},
{"learn":[0.4750173038],"iteration":546,"passed_time":7.291348932,"remaining_time":6.038356611},
{"learn":[0.4747260441],"iteration":547,"passed_time":7.302909171,"remaining_time":6.023567418},
{"learn":[0.4744379923],"iteration":548,"passed_time":7.31519314,"remaining_time":6.009384528},
{"learn":[0.4741134252],"iteration":549,"passed_time":7.327086958,"remaining_time":5.994889329},
{"learn":[0.4739322651],"iteration":550,"passed_time":7.338407693,"remaining_time":5.979936577},
{"learn":[0.4735870733],"iteration":551,"passed_time":7.350482209,"remaining_time":5.965608749},
{"learn":[0.4732140368],"iteration":552,"passed_time":7.363038212,"remaining_time":5.951678265},
{"learn":[0.4729218122],"iteration":553,"passed_time":7.376199344,"remaining_time":5.938239905},
{"learn":[0.4724794996],"iteration":554,"passed_time":7.38863596,"remaining_time":5.924221626},
{"learn":[0.4723689011],"iteration":555,"passed_time":7.400280703,"remaining_time":5.909576676},
{"learn":[0.4718667542],"iteration":556,"passed_time":7.412568436,"remaining_time":5.895453891},
{"learn":[0.4715673041],"iteration":557,"passed_time":7.425402901,"remaining_time":5.881770757},
{"learn":[0.4713102473],"iteration":558,"passed_time":7.437160107,"remaining_time":5.8672408},
{"learn":[0.4710275873],"iteration":559,"passed_time":7.449185518,"remaining_time":5.852931478},
{"learn":[0.4707016724],"iteration":560,"passed_time":7.461574175,"remaining_time":5.83891455},
{"learn":[0.470388677],"iteration":561,"passed_time":7.474009103,"remaining_time":5.824939479},
{"learn":[0.4699770562],"iteration":562,"passed_time":7.485877176,"remaining_time":5.810529886},
{"learn":[0.4696816283],"iteration":563,"passed_time":7.498399698,"remaining_time":5.796635228},
{"learn":[0.4694795812],"iteration":564,"passed_time":7.510772555,"remaining_time":5.782630197},
{"learn":[0.4691440886],"iteration":565,"passed_time":7.523545327,"remaining_time":5.768937583},
{"learn":[0.4687144173],"iteration":566,"passed_time":7.535599451,"remaining_time":5.754699405},
{"learn":[0.4684459871],"iteration":567,"passed_time":7.547322,"remaining_time":5.740216732},
{"learn":[0.4681598387],"iteration":568,"passed_time":7.559626333,"remaining_time":5.726184445},
{"learn":[0.4679487397],"iteration":569,"passed_time":7.570934832,"remaining_time":5.711406979},
{"learn":[0.4676535372],"iteration":570,"passed_time":7.581744329,"remaining_time":5.696266755},
{"learn":[0.4671722324],"iteration":571,"passed_time":7.594661536,"remaining_time":5.682718772},
{"learn":[0.4669055614],"iteration":572,"passed_time":7.607195857,"remaining_time":5.668887663},
{"learn":[0.466453942],"iteration":573,"passed_time":7.619279304,"remaining_time":5.654726452},
{"learn":[0.4659304847],"iteration":574,"passed_time":7.631490798,"remaining_time":5.640667112},
{"learn":[0.4655083967],"iteration":575,"passed_time":7.643617789,"remaining_time":5.626551983},
{"learn":[0.4651000706],"iteration":576,"passed_time":7.655525275,"remaining_time":5.612282827},
{"learn":[0.4648575381],"iteration":577,"passed_time":7.667323577,"remaining_time":5.597942127},
{"learn":[0.4645349551],"iteration":578,"passed_time":7.678997455,"remaining_time":5.583519739},
{"learn":[0.4642237213],"iteration":579,"passed_time":7.69140078,"remaining_time":5.569635048},
{"learn":[0.4639191606],"iteration":580,"passed_time":7.703470791,"remaining_time":5.55551508},
{"learn":[0.4635331147],"iteration":581,"passed_time":7.715391799,"remaining_time":5.541295141},
{"learn":[0.4631571058],"iteration":582,"passed_time":7.727189859,"remaining_time":5.526995148},
{"learn":[0.4627158601],"iteration":583,"passed_time":7.740389486,"remaining_time":5.5137021},
{"learn":[0.4623842209],"iteration":584,"passed_time":7.752853523,"remaining_time":5.499887542},
{"learn":[0.4620782933],"iteration":585,"passed_time":7.764081594,"remaining_time":5.485204403},
{"learn":[0.4616587386],"iteration":586,"passed_time":7.776163267,"remaining_time":5.47113361},
{"learn":[0.4613762433],"iteration":587,"passed_time":7.788417852,"remaining_time":5.45719074},
{"learn":[0.461279376],"iteration":588,"passed_time":7.80072564,"remaining_time":5.443290726},
{"learn":[0.4608645957],"iteration":589,"passed_time":7.813985337,"remaining_time":5.430057607},
{"learn":[0.4604575785],"iteration":590,"passed_time":7.825481398,"remaining_time":5.415603878},
{"learn":[0.4600629085],"iteration":591,"passed_time":7.837645339,"remaining_time":5.401620436},
{"learn":[0.4595930511],"iteration":592,"passed_time":7.850242687,"remaining_time":5.387940596},
{"learn":[0.4589884684],"iteration":593,"passed_time":7.8622655,"remaining_time":5.373871705},
{"learn":[0.4588322745],"iteration":594,"passed_time":7.87415207,"remaining_time":5.359716955},
{"learn":[0.4584671827],"iteration":595,"passed_time":7.886719277,"remaining_time":5.346031187},
{"learn":[0.4580607106],"iteration":596,"passed_time":7.898507772,"remaining_time":5.331823504},
{"learn":[0.45772394],"iteration":597,"passed_time":7.90978699,"remaining_time":5.317281555},
{"learn":[0.457330886],"iteration":598,"passed_time":7.936529901,"remaining_time":5.313102655},
{"learn":[0.456981726],"iteration":599,"passed_time":7.948536708,"remaining_time":5.299024472},
{"learn":[0.4566571938],"iteration":600,"passed_time":7.959528509,"remaining_time":5.284279326},
{"learn":[0.456330299],"iteration":601,"passed_time":7.986121007,"remaining_time":5.279860732},
{"learn":[0.4562558533],"iteration":602,"passed_time":7.997073966,"remaining_time":5.265071915},
{"learn":[0.4560131269],"iteration":603,"passed_time":8.008029537,"remaining_time":5.250297511},
{"learn":[0.4556420636],"iteration":604,"passed_time":8.020144313,"remaining_time":5.236292568},
{"learn":[0.4552645611],"iteration":605,"passed_time":8.031547058,"remaining_time":5.221830926},
{"learn":[0.4548590253],"iteration":606,"passed_time":8.042967395,"remaining_time":5.207390752},
{"learn":[0.4544818378],"iteration":607,"passed_time":8.055339282,"remaining_time":5.193574011},
{"learn":[0.4540730007],"iteration":608,"passed_time":8.070112005,"remaining_time":5.181303438},
{"learn":[0.4537930043],"iteration":609,"passed_time":8.082681394,"remaining_time":5.167615973},
{"learn":[0.453518267],"iteration":610,"passed_time":8.095242903,"remaining_time":5.153927151},
{"learn":[0.4530686048],"iteration":611,"passed_time":8.107535508,"remaining_time":5.140071531},
{"learn":[0.4528191532],"iteration":612,"passed_time":8.12264147,"remaining_time":5.127997143},
{"learn":[0.452574994],"iteration":613,"passed_time":8.136284724,"remaining_time":5.114993328},
{"learn":[0.4522236914],"iteration":614,"passed_time":8.168689213,"remaining_time":5.113732272},
{"learn":[0.451815328],"iteration":615,"passed_time":8.18132518,"remaining_time":5.100046865},
{"learn":[0.4513416183],"iteration":616,"passed_time":8.194085139,"remaining_time":5.086441828},
{"learn":[0.4509294682],"iteration":617,"passed_time":8.206473095,"remaining_time":5.072609583},
{"learn":[0.4506576064],"iteration":618,"passed_time":8.219647223,"remaining_time":5.0592659},
{"learn":[0.4501268909],"iteration":619,"passed_time":8.232067479,"remaining_time":5.045460713},
{"learn":[0.4497945432],"iteration":620,"passed_time":8.244880723,"remaining_time":5.031899829},
{"learn":[0.4494262776],"iteration":621,"passed_time":8.257113749,"remaining_time":5.017988741},
{"learn":[0.4490925049],"iteration":622,"passed_time":8.268864402,"remaining_time":5.003791139},
{"learn":[0.4487432609],"iteration":623,"passed_time":8.281172765,"remaining_time":4.989937436},
{"learn":[0.4486440609],"iteration":624,"passed_time":8.293389312,"remaining_time":4.976033587},
{"learn":[0.4483800974],"iteration":625,"passed_time":8.304299201,"remaining_time":4.961354475},
{"learn":[0.448125381],"iteration":626,"passed_time":8.31620927,"remaining_time":4.947282389},
{"learn":[0.4477717014],"iteration":627,"passed_time":8.328908959,"remaining_time":4.933684925},
{"learn":[0.4473897046],"iteration":628,"passed_time":8.340961178,"remaining_time":4.919708421},
{"learn":[0.4469081431],"iteration":629,"passed_time":8.352333591,"remaining_time":4.905338776},
{"learn":[0.4465496757],"iteration":630,"passed_time":8.369538643,"remaining_time":4.894389476},
{"learn":[0.4460015693],"iteration":631,"passed_time":8.385523927,"remaining_time":4.882710135},
{"learn":[0.4455757569],"iteration":632,"passed_time":8.398114522,"remaining_time":4.86904902},
{"learn":[0.4451243238],"iteration":633,"passed_time":8.410677373,"remaining_time":4.855375266},
{"learn":[0.4447613881],"iteration":634,"passed_time":8.421977292,"remaining_time":4.840979074},
{"learn":[0.4444619205],"iteration":635,"passed_time":8.433700482,"remaining_time":4.826834867},
{"learn":[0.4442494018],"iteration":636,"passed_time":8.446846419,"remaining_time":4.813509027},
{"learn":[0.4438463172],"iteration":637,"passed_time":8.459051001,"remaining_time":4.799649627},
{"learn":[0.4434495983],"iteration":638,"passed_time":8.471712563,"remaining_time":4.786053576},
{"learn":[0.4431233358],"iteration":639,"passed_time":8.483444708,"remaining_time":4.771937648},
{"learn":[0.4426789115],"iteration":640,"passed_time":8.495200502,"remaining_time":4.757842403},
{"learn":[0.4422049392],"iteration":641,"passed_time":8.508154225,"remaining_time":4.744422449},
{"learn":[0.4421482559],"iteration":642,"passed_time":8.520452731,"remaining_time":4.730640163},
{"learn":[0.4419388065],"iteration":643,"passed_time":8.53126457,"remaining_time":4.716040663},
{"learn":[0.4415709106],"iteration":644,"passed_time":8.543661017,"remaining_time":4.702325056},
{"learn":[0.4412550709],"iteration":645,"passed_time":8.556438865,"remaining_time":4.688822536},
{"learn":[0.4409629196],"iteration":646,"passed_time":8.567647895,"remaining_time":4.674466317},
{"learn":[0.4405871884],"iteration":647,"passed_time":8.579060637,"remaining_time":4.660230469},
{"learn":[0.4402343782],"iteration":648,"passed_time":8.59138819,"remaining_time":4.646498081},
{"learn":[0.4399907992],"iteration":649,"passed_time":8.603155263,"remaining_time":4.632468218},
{"learn":[0.4395996241],"iteration":650,"passed_time":8.614963631,"remaining_time":4.618467446},
{"learn":[0.4392665609],"iteration":651,"passed_time":8.628177859,"remaining_time":4.605223765},
{"learn":[0.4388383177],"iteration":652,"passed_time":8.64046871,"remaining_time":4.591489498},
{"learn":[0.4383435516],"iteration":653,"passed_time":8.653471678,"remaining_time":4.578136392},
{"learn":[0.4380055775],"iteration":654,"passed_time":8.665537808,"remaining_time":4.564290907},
{"learn":[0.4377427722],"iteration":655,"passed_time":8.677054954,"remaining_time":4.550162964},
{"learn":[0.4375150605],"iteration":656,"passed_time":8.689331404,"remaining_time":4.536439378},
{"learn":[0.4372860747],"iteration":657,"passed_time":8.702077645,"remaining_time":4.522964369},
{"learn":[0.4369780716],"iteration":658,"passed_time":8.713458128,"remaining_time":4.508784859},
{"learn":[0.4366544665],"iteration":659,"passed_time":8.725587067,"remaining_time":4.494999398},
{"learn":[0.4362054754],"iteration":660,"passed_time":8.73792034,"remaining_time":4.481323745},
{"learn":[0.435963471],"iteration":661,"passed_time":8.749970682,"remaining_time":4.46750769},
{"learn":[0.4355727475],"iteration":662,"passed_time":8.762165576,"remaining_time":4.453770436},
{"learn":[0.4351047225],"iteration":663,"passed_time":8.774529282,"remaining_time":4.440123251},
{"learn":[0.4346182924],"iteration":664,"passed_time":8.800584417,"remaining_time":4.433377113},
{"learn":[0.4343011392],"iteration":665,"passed_time":8.811334135,"remaining_time":4.418897299},
{"learn":[0.4339772483],"iteration":666,"passed_time":8.822938114,"remaining_time":4.40485516},
{"learn":[0.4336233966],"iteration":667,"passed_time":8.83514756,"remaining_time":4.391121242},
{"learn":[0.4332385108],"iteration":668,"passed_time":8.846899285,"remaining_time":4.377165416},
{"learn":[0.4329238785],"iteration":669,"passed_time":8.858437666,"remaining_time":4.363111089},
{"learn":[0.4324318755],"iteration":670,"passed_time":8.870633938,"remaining_time":4.349386834},
{"learn":[0.4320616211],"iteration":671,"passed_time":8.883023325,"remaining_time":4.335761385},
{"learn":[0.4316897673],"iteration":672,"passed_time":8.893993889,"remaining_time":4.321450226},
{"learn":[0.4313386067],"iteration":673,"passed_time":8.907661169,"remaining_time":4.308453325},
{"learn":[0.431042756],"iteration":674,"passed_time":8.933440529,"remaining_time":4.301286181},
{"learn":[0.4307079516],"iteration":675,"passed_time":8.943609078,"remaining_time":4.286581866},
{"learn":[0.4303706826],"iteration":676,"passed_time":8.954044089,"remaining_time":4.272018081},
{"learn":[0.4300510456],"iteration":677,"passed_time":8.966675424,"remaining_time":4.258509567},
{"learn":[0.4297709572],"iteration":678,"passed_time":8.978940875,"remaining_time":4.244830664},
{"learn":[0.4295550052],"iteration":679,"passed_time":8.989654229,"remaining_time":4.230425519},
{"learn":[0.4292485552],"iteration":680,"passed_time":9.0017126,"remaining_time":4.216661262},
{"learn":[0.4289847147],"iteration":681,"passed_time":9.013623815,"remaining_time":4.202833392},
{"learn":[0.4286689415],"iteration":682,"passed_time":9.025953445,"remaining_time":4.189205332},
{"learn":[0.4282821459],"iteration":683,"passed_time":9.038839954,"remaining_time":4.175838341},
{"learn":[0.42784631],"iteration":684,"passed_time":9.052263854,"remaining_time":4.162719874},
{"learn":[0.4275800817],"iteration":685,"passed_time":9.065211378,"remaining_time":4.149382467},
{"learn":[0.4272649005],"iteration":686,"passed_time":9.07765345,"remaining_time":4.13581591},
{"learn":[0.4269254764],"iteration":687,"passed_time":9.089847429,"remaining_time":4.122140113},
{"learn":[0.426656022],"iteration":688,"passed_time":9.107390271,"remaining_time":4.110882981},
{"learn":[0.4262914139],"iteration":689,"passed_time":9.119493947,"remaining_time":4.097163947},
{"learn":[0.4260183113],"iteration":690,"passed_time":9.132555977,"remaining_time":4.083878143},
{"learn":[0.425675178],"iteration":691,"passed_time":9.144587771,"remaining_time":4.070134442},
{"learn":[0.4253672032],"iteration":692,"passed_time":9.156214527,"remaining_time":4.056216248},
{"learn":[0.4248174965],"iteration":693,"passed_time":9.168649437,"remaining_time":4.042660991},
{"learn":[0.4245354836],"iteration":694,"passed_time":9.183071483,"remaining_time":4.029981011},
{"learn":[0.4240906151],"iteration":695,"passed_time":9.196973305,"remaining_time":4.0170688},
{"learn":[0.4240426065],"iteration":696,"passed_time":9.21125173,"remaining_time":4.004317466},
{"learn":[0.4235403429],"iteration":697,"passed_time":9.223330726,"remaining_time":3.990610142},
{"learn":[0.4234936755],"iteration":698,"passed_time":9.23466668,"remaining_time":3.976587511},
{"learn":[0.423123114],"iteration":699,"passed_time":9.247034025,"remaining_time":3.963014582},
{"learn":[0.4229359786],"iteration":700,"passed_time":9.25894267,"remaining_time":3.949249441},
{"learn":[0.4226514902],"iteration":701,"passed_time":9.271830057,"remaining_time":3.935905067},
{"learn":[0.422193074],"iteration":702,"passed_time":9.284508682,"remaining_time":3.922473796},
{"learn":[0.4218767828],"iteration":703,"passed_time":9.296525892,"remaining_time":3.908766568},
{"learn":[0.4214664152],"iteration":704,"passed_time":9.308107427,"remaining_time":3.894881831},
{"learn":[0.4211862905],"iteration":705,"passed_time":9.31925548,"remaining_time":3.880823103},
{"learn":[0.4208354521],"iteration":706,"passed_time":9.331923811,"remaining_time":3.867402654},
{"learn":[0.4204783669],"iteration":707,"passed_time":9.343825509,"remaining_time":3.853668148},
{"learn":[0.4200671257],"iteration":708,"passed_time":9.355822595,"remaining_time":3.839977962},
{"learn":[0.4197174129],"iteration":709,"passed_time":9.367862374,"remaining_time":3.826309984},
{"learn":[0.4192943974],"iteration":710,"passed_time":9.380580165,"remaining_time":3.812922177},
{"learn":[0.4187882055],"iteration":711,"passed_time":9.393979705,"remaining_time":3.799812016},
{"learn":[0.4184742531],"iteration":712,"passed_time":9.406538201,"remaining_time":3.786362502},
{"learn":[0.4181478844],"iteration":713,"passed_time":9.418130219,"remaining_time":3.772528351},
{"learn":[0.4179468313],"iteration":714,"passed_time":9.430423529,"remaining_time":3.758980008},
{"learn":[0.4178077513],"iteration":715,"passed_time":9.442875399,"remaining_time":3.745498063},
{"learn":[0.4174820298],"iteration":716,"passed_time":9.455114877,"remaining_time":3.731935161},
{"learn":[0.4171796887],"iteration":717,"passed_time":9.466731231,"remaining_time":3.718131208},
{"learn":[0.4167707485],"iteration":718,"passed_time":9.478751039,"remaining_time":3.704491018},
{"learn":[0.4164052167],"iteration":719,"passed_time":9.490841635,"remaining_time":3.690882858},
{"learn":[0.415938012],"iteration":720,"passed_time":9.503078361,"remaining_time":3.677335455},
{"learn":[0.4155143032],"iteration":721,"passed_time":9.514942299,"remaining_time":3.663648143},
{"learn":[0.4152181838],"iteration":722,"passed_time":9.527327006,"remaining_time":3.650165395},
{"learn":[0.414905086],"iteration":723,"passed_time":9.539956315,"remaining_time":3.636778927},
{"learn":[0.4144937721],"iteration":724,"passed_time":9.552625256,"remaining_time":3.62340958},
{"learn":[0.4141600999],"iteration":725,"passed_time":9.568491288,"remaining_time":3.611248778},
{"learn":[0.4138180004],"iteration":726,"passed_time":9.579678528,"remaining_time":3.597320823},
{"learn":[0.4134025182],"iteration":727,"passed_time":9.592369036,"remaining_time":3.583962057},
{"learn":[0.4131607906],"iteration":728,"passed_time":9.60473467,"remaining_time":3.570484356},
{"learn":[0.4128710677],"iteration":729,"passed_time":9.616295945,"remaining_time":3.556712199},
{"learn":[0.4125941284],"iteration":730,"passed_time":9.627976282,"remaining_time":3.542989904},
{"learn":[0.4123340693],"iteration":731,"passed_time":9.63974107,"remaining_time":3.529304108},
{"learn":[0.4119759164],"iteration":732,"passed_time":9.651855328,"remaining_time":3.515750849},
{"learn":[0.4114915004],"iteration":733,"passed_time":9.664533701,"remaining_time":3.502405946},
{"learn":[0.411245268],"iteration":734,"passed_time":9.675946454,"remaining_time":3.488606545},
{"learn":[0.4110191542],"iteration":735,"passed_time":9.687721076,"remaining_time":3.474943429},
{"learn":[0.4105578505],"iteration":736,"passed_time":9.701463011,"remaining_time":3.461987479},
{"learn":[0.4102574604],"iteration":737,"passed_time":9.729189981,"remaining_time":3.453994275},
{"learn":[0.4102133323],"iteration":738,"passed_time":9.739586465,"remaining_time":3.439826884},
{"learn":[0.4098214714],"iteration":739,"passed_time":9.762063752,"remaining_time":3.429914291},
{"learn":[0.4095539148],"iteration":740,"passed_time":9.772280656,"remaining_time":3.415682442},
{"learn":[0.4093536855],"iteration":741,"passed_time":9.783128443,"remaining_time":3.401680779},
{"learn":[0.4090239114],"iteration":742,"passed_time":9.796254116,"remaining_time":3.388475515},
{"learn":[0.4086527849],"iteration":743,"passed_time":9.808293554,"remaining_time":3.374896707},
{"learn":[0.4083822008],"iteration":744,"passed_time":9.820847699,"remaining_time":3.361498206},
{"learn":[0.4080867794],"iteration":745,"passed_time":9.832921715,"remaining_time":3.347938493},
{"learn":[0.4077058015],"iteration":746,"passed_time":9.845789491,"remaining_time":3.334651595},
{"learn":[0.4072366541],"iteration":747,"passed_time":9.859075842,"remaining_time":3.321506834},
{"learn":[0.4069865378],"iteration":748,"passed_time":9.870349709,"remaining_time":3.307687286},
{"learn":[0.4064800179],"iteration":749,"passed_time":9.882278345,"remaining_time":3.294092782},
{"learn":[0.4063637718],"iteration":750,"passed_time":9.895407298,"remaining_time":3.280900689},
{"learn":[0.4060258809],"iteration":751,"passed_time":9.908043294,"remaining_time":3.267546193},
{"learn":[0.4056899874],"iteration":752,"passed_time":9.919439442,"remaining_time":3.253786908},
{"learn":[0.4052073525],"iteration":753,"passed_time":9.931936197,"remaining_time":3.240392977},
{"learn":[0.40491923],"iteration":754,"passed_time":9.94429736,"remaining_time":3.226957421},
{"learn":[0.4045606251],"iteration":755,"passed_time":9.956764699,"remaining_time":3.213558977},
{"learn":[0.4039876563],"iteration":756,"passed_time":9.969171893,"remaining_time":3.200143686},
{"learn":[0.4036663732],"iteration":757,"passed_time":9.980582138,"remaining_time":3.186412767},
{"learn":[0.403339186],"iteration":758,"passed_time":9.993032562,"remaining_time":3.173018244},
{"learn":[0.4031097227],"iteration":759,"passed_time":10.0056168,"remaining_time":3.159668463},
{"learn":[0.4027911517],"iteration":760,"passed_time":10.01817175,"remaining_time":3.146311496},
{"learn":[0.4024421474],"iteration":761,"passed_time":10.03238184,"remaining_time":3.133473592},
{"learn":[0.4022735554],"iteration":762,"passed_time":10.04548809,"remaining_time":3.120289222},
{"learn":[0.4018472495],"iteration":763,"passed_time":10.06765399,"remaining_time":3.109903589},
{"learn":[0.4015265985],"iteration":764,"passed_time":10.0801431,"remaining_time":3.096514546},
{"learn":[0.4012605563],"iteration":765,"passed_time":10.09323447,"remaining_time":3.083311836},
{"learn":[0.4009188993],"iteration":766,"passed_time":10.10655273,"remaining_time":3.07017834},
{"learn":[0.4006279065],"iteration":767,"passed_time":10.11886349,"remaining_time":3.056740014},
{"learn":[0.4002921275],"iteration":768,"passed_time":10.13089756,"remaining_time":3.043221504},
{"learn":[0.4000221207],"iteration":769,"passed_time":10.14352089,"remaining_time":3.029882862},
{"learn":[0.3998390753],"iteration":770,"passed_time":10.15679087,"remaining_time":3.016738144},
{"learn":[0.3994205774],"iteration":771,"passed_time":10.171575,"remaining_time":3.004040284},
{"learn":[0.3990135788],"iteration":772,"passed_time":10.18562584,"remaining_time":2.99112169},
{"learn":[0.3988275614],"iteration":773,"passed_time":10.19750039,"remaining_time":2.977564714},
{"learn":[0.3985914959],"iteration":774,"passed_time":10.22350237,"remaining_time":2.968113591},
{"learn":[0.39817272],"iteration":775,"passed_time":10.23544309,"remaining_time":2.954560893},
{"learn":[0.3979143584],"iteration":776,"passed_time":10.24656452,"remaining_time":2.940777206},
{"learn":[0.3975964797],"iteration":777,"passed_time":10.25817858,"remaining_time":2.927140931},
{"learn":[0.3975477216],"iteration":778,"passed_time":10.27017742,"remaining_time":2.913619011},
{"learn":[0.3971770045],"iteration":779,"passed_time":10.28256011,"remaining_time":2.900209261},
{"learn":[0.3968342668],"iteration":780,"passed_time":10.29348372,"remaining_time":2.886393003},
{"learn":[0.396482267],"iteration":781,"passed_time":10.30569399,"remaining_time":2.872942825},
{"learn":[0.3960918445],"iteration":782,"passed_time":10.31806061,"remaining_time":2.859539148},
{"learn":[0.3960556262],"iteration":783,"passed_time":10.32887568,"remaining_time":2.845710648},
{"learn":[0.3958763084],"iteration":784,"passed_time":10.34078663,"remaining_time":2.83218997},
{"learn":[0.3955241879],"iteration":785,"passed_time":10.35377393,"remaining_time":2.81896644},
{"learn":[0.3951713549],"iteration":786,"passed_time":10.36592822,"remaining_time":2.805518057},
{"learn":[0.3950383393],"iteration":787,"passed_time":10.37725534,"remaining_time":2.791850422},
{"learn":[0.3948244605],"iteration":788,"passed_time":10.38998875,"remaining_time":2.778564799},
{"learn":[0.3944212615],"iteration":789,"passed_time":10.40218318,"remaining_time":2.765137302},
{"learn":[0.3943187974],"iteration":790,"passed_time":10.41439782,"remaining_time":2.75171826},
{"learn":[0.3938911589],"iteration":791,"passed_time":10.42590195,"remaining_time":2.738115663},
{"learn":[0.3938439027],"iteration":792,"passed_time":10.43851488,"remaining_time":2.724807795},
{"learn":[0.3935132929],"iteration":793,"passed_time":10.45061239,"remaining_time":2.71136795},
{"learn":[0.3933212789],"iteration":794,"passed_time":10.46288334,"remaining_time":2.697976206},
{"learn":[0.3931119954],"iteration":795,"passed_time":10.4734886,"remaining_time":2.684160395},
{"learn":[0.3928663356],"iteration":796,"passed_time":10.48500329,"remaining_time":2.670584277},
{"learn":[0.3925004271],"iteration":797,"passed_time":10.49845695,"remaining_time":2.65750414},
{"learn":[0.392285993],"iteration":798,"passed_time":10.5094905,"remaining_time":2.643814257},
{"learn":[0.3919282239],"iteration":799,"passed_time":10.52202704,"remaining_time":2.630506759},
{"learn":[0.3914887562],"iteration":800,"passed_time":10.53500463,"remaining_time":2.617310763},
{"learn":[0.3914463636],"iteration":801,"passed_time":10.54688054,"remaining_time":2.603843326},
{"learn":[0.3911929463],"iteration":802,"passed_time":10.55848919,"remaining_time":2.590314285},
{"learn":[0.3908132065],"iteration":803,"passed_time":10.57108292,"remaining_time":2.577030165},
{"learn":[0.3906616056],"iteration":804,"passed_time":10.58318923,"remaining_time":2.56362969},
{"learn":[0.3904209873],"iteration":805,"passed_time":10.59538033,"remaining_time":2.550252833},
{"learn":[0.3901155105],"iteration":806,"passed_time":10.60769596,"remaining_time":2.5369087},
{"learn":[0.3896889199],"iteration":807,"passed_time":10.61951602,"remaining_time":2.523449352},
{"learn":[0.389402253],"iteration":808,"passed_time":10.63216213,"remaining_time":2.510189081},
{"learn":[0.3890377106],"iteration":809,"passed_time":10.64486668,"remaining_time":2.496944037},
{"learn":[0.3888931826],"iteration":810,"passed_time":10.65692095,"remaining_time":2.483548778},
{"learn":[0.3886879211],"iteration":811,"passed_time":10.66917715,"remaining_time":2.470203577},
{"learn":[0.3882925013],"iteration":812,"passed_time":10.68186186,"remaining_time":2.456959617},
{"learn":[0.3879559693],"iteration":813,"passed_time":10.69523233,"remaining_time":2.443873726},
{"learn":[0.3875985202],"iteration":814,"passed_time":10.70718651,"remaining_time":2.43046565},
{"learn":[0.3874906581],"iteration":815,"passed_time":10.71883399,"remaining_time":2.416991978},
{"learn":[0.3871350116],"iteration":816,"passed_time":10.73179283,"remaining_time":2.40381651},
{"learn":[0.3870967615],"iteration":817,"passed_time":10.74402105,"remaining_time":2.390479011},
{"learn":[0.3867780191],"iteration":818,"passed_time":10.77726789,"remaining_time":2.381789364},
{"learn":[0.3864888802],"iteration":819,"passed_time":10.78730438,"remaining_time":2.367944863},
{"learn":[0.3861763842],"iteration":820,"passed_time":10.79918919,"remaining_time":2.354512624},
{"learn":[0.3858983447],"iteration":821,"passed_time":10.81047246,"remaining_time":2.340953891},
{"learn":[0.3855391706],"iteration":822,"passed_time":10.82131009,"remaining_time":2.327304842},
{"learn":[0.3852574935],"iteration":823,"passed_time":10.83327394,"remaining_time":2.313903171},
{"learn":[0.3849396622],"iteration":824,"passed_time":10.84542796,"remaining_time":2.300545326},
{"learn":[0.3846965234],"iteration":825,"passed_time":10.85728519,"remaining_time":2.287127874},
{"learn":[0.3843906283],"iteration":826,"passed_time":10.87015664,"remaining_time":2.273926359},
{"learn":[0.3840666511],"iteration":827,"passed_time":10.88217512,"remaining_time":2.260548455},
{"learn":[0.3837601887],"iteration":828,"passed_time":10.89444171,"remaining_time":2.247225009},
{"learn":[0.3835103777],"iteration":829,"passed_time":10.90694011,"remaining_time":2.233951589},
{"learn":[0.3832203207],"iteration":830,"passed_time":10.91824432,"remaining_time":2.220437171},
{"learn":[0.3831854167],"iteration":831,"passed_time":10.93138171,"remaining_time":2.20729823},
{"learn":[0.3829174279],"iteration":832,"passed_time":10.94373064,"remaining_time":2.194001221},
{"learn":[0.3825811923],"iteration":833,"passed_time":10.95578924,"remaining_time":2.180648698},
{"learn":[0.3822708772],"iteration":834,"passed_time":10.96678776,"remaining_time":2.167089797},
{"learn":[0.3820164317],"iteration":835,"passed_time":10.97985277,"remaining_time":2.153942409},
{"learn":[0.3817850543],"iteration":836,"passed_time":10.99229364,"remaining_time":2.140673671},
{"learn":[0.3814584428],"iteration":837,"passed_time":11.006201,"remaining_time":2.127690408},
{"learn":[0.3810043748],"iteration":838,"passed_time":11.02072055,"remaining_time":2.114822418},
{"learn":[0.3807432045],"iteration":839,"passed_time":11.03193471,"remaining_time":2.101320898},
{"learn":[0.380443761],"iteration":840,"passed_time":11.05738501,"remaining_time":2.090516309},
{"learn":[0.3802252547],"iteration":841,"passed_time":11.06985993,"remaining_time":2.077242125},
{"learn":[0.379791809],"iteration":842,"passed_time":11.08203443,"remaining_time":2.063913886},
{"learn":[0.3794368535],"iteration":843,"passed_time":11.09420308,"remaining_time":2.050587299},
{"learn":[0.3791802178],"iteration":844,"passed_time":11.10673015,"remaining_time":2.037329199},
{"learn":[0.3788327452],"iteration":845,"passed_time":11.11957666,"remaining_time":2.024130975},
{"learn":[0.3784694058],"iteration":846,"passed_time":11.13201764,"remaining_time":2.010860329},
{"learn":[0.3781420102],"iteration":847,"passed_time":11.14425264,"remaining_time":1.997554718},
{"learn":[0.3779006091],"iteration":848,"passed_time":11.16670095,"remaining_time":1.986068131},
{"learn":[0.3775518044],"iteration":849,"passed_time":11.18125248,"remaining_time":1.973162203},
{"learn":[0.3771859976],"iteration":850,"passed_time":11.19332863,"remaining_time":1.959818997},
{"learn":[0.3768766829],"iteration":851,"passed_time":11.20557471,"remaining_time":1.946508282},
{"learn":[0.3765505355],"iteration":852,"passed_time":11.21674949,"remaining_time":1.933015445},
{"learn":[0.3762179976],"iteration":853,"passed_time":11.22766711,"remaining_time":1.919484073},
{"learn":[0.3759837536],"iteration":854,"passed_time":11.24015226,"remaining_time":1.906224652},
{"learn":[0.3756397969],"iteration":855,"passed_time":11.25232545,"remaining_time":1.892914561},
{"learn":[0.3753660941],"iteration":856,"passed_time":11.26334703,"remaining_time":1.879414966},
{"learn":[0.3751129255],"iteration":857,"passed_time":11.27537408,"remaining_time":1.866087552},
{"learn":[0.3748614936],"iteration":858,"passed_time":11.28753371,"remaining_time":1.852784928},
{"learn":[0.3745098821],"iteration":859,"passed_time":11.29969304,"remaining_time":1.839484914},
{"learn":[0.3742577535],"iteration":860,"passed_time":11.31175277,"remaining_time":1.826171469},
{"learn":[0.3740812197],"iteration":861,"passed_time":11.32279287,"remaining_time":1.812697698},
{"learn":[0.3740482128],"iteration":862,"passed_time":11.33460193,"remaining_time":1.799351639},
{"learn":[0.3737298422],"iteration":863,"passed_time":11.34646467,"remaining_time":1.786017587},
{"learn":[0.3734360543],"iteration":864,"passed_time":11.35755671,"remaining_time":1.772566654},
{"learn":[0.3732507627],"iteration":865,"passed_time":11.36971961,"remaining_time":1.759286867},
{"learn":[0.3729340656],"iteration":866,"passed_time":11.3829306,"remaining_time":1.746170439},
{"learn":[0.3726589618],"iteration":867,"passed_time":11.39445652,"remaining_time":1.732797535},
{"learn":[0.3723336528],"iteration":868,"passed_time":11.40609929,"remaining_time":1.719446498},
{"learn":[0.3718571567],"iteration":869,"passed_time":11.418972,"remaining_time":1.706283173},
{"learn":[0.3716146694],"iteration":870,"passed_time":11.43125484,"remaining_time":1.69303315},
{"learn":[0.3713208987],"iteration":871,"passed_time":11.44356754,"remaining_time":1.67978973},
{"learn":[0.3709662697],"iteration":872,"passed_time":11.45580078,"remaining_time":1.666536883},
{"learn":[0.3708045649],"iteration":873,"passed_time":11.46757841,"remaining_time":1.653220686},
{"learn":[0.370531744],"iteration":874,"passed_time":11.47948665,"remaining_time":1.639926664},
{"learn":[0.3702717231],"iteration":875,"passed_time":11.49145301,"remaining_time":1.626644033},
{"learn":[0.369972741],"iteration":876,"passed_time":11.50441194,"remaining_time":1.613503614},
{"learn":[0.3697096427],"iteration":877,"passed_time":11.51765415,"remaining_time":1.600402969},
{"learn":[0.3693371732],"iteration":878,"passed_time":11.53005505,"remaining_time":1.587186191},
{"learn":[0.3690421236],"iteration":879,"passed_time":11.54136064,"remaining_time":1.573821905},
{"learn":[0.3687380689],"iteration":880,"passed_time":11.55375341,"remaining_time":1.560609143},
{"learn":[0.3683726506],"iteration":881,"passed_time":11.56615051,"remaining_time":1.547398822},
{"learn":[0.3680347288],"iteration":882,"passed_time":11.57859583,"remaining_time":1.534196729},
{"learn":[0.3677538618],"iteration":883,"passed_time":11.59027234,"remaining_time":1.520895465},
{"learn":[0.3674883945],"iteration":884,"passed_time":11.60211993,"remaining_time":1.507620104},
{"learn":[0.3672553356],"iteration":885,"passed_time":11.61414646,"remaining_time":1.49437099},
{"learn":[0.3668612761],"iteration":886,"passed_time":11.62715892,"remaining_time":1.481250234},
{"learn":[0.3665967641],"iteration":887,"passed_time":11.63932376,"remaining_time":1.468022817},
{"learn":[0.3664048063],"iteration":888,"passed_time":11.65054475,"remaining_time":1.454679941},
{"learn":[0.3660602114],"iteration":889,"passed_time":11.66307189,"remaining_time":1.441503267},
{"learn":[0.3660377057],"iteration":890,"passed_time":11.67456837,"remaining_time":1.428201967},
{"learn":[0.3657449662],"iteration":891,"passed_time":11.68577375,"remaining_time":1.414869468},
{"learn":[0.3657144838],"iteration":892,"passed_time":11.69812263,"remaining_time":1.401678747},
{"learn":[0.3654763182],"iteration":893,"passed_time":11.7107969,"remaining_time":1.388528491},
{"learn":[0.3652528315],"iteration":894,"passed_time":11.72241934,"remaining_time":1.375255901},
{"learn":[0.3649813774],"iteration":895,"passed_time":11.74845393,"remaining_time":1.363659831},
{"learn":[0.3647538773],"iteration":896,"passed_time":11.75946125,"remaining_time":1.35030603},
{"learn":[0.3644485987],"iteration":897,"passed_time":11.7696551,"remaining_time":1.336865056},
{"learn":[0.3642410301],"iteration":898,"passed_time":11.78087024,"remaining_time":1.323546044},
{"learn":[0.3639725737],"iteration":899,"passed_time":11.79213554,"remaining_time":1.310237283},
{"learn":[0.3637119345],"iteration":900,"passed_time":11.8032429,"remaining_time":1.296915701},
{"learn":[0.3634403266],"iteration":901,"passed_time":11.81573801,"remaining_time":1.283749806},
{"learn":[0.3634107589],"iteration":902,"passed_time":11.82675377,"remaining_time":1.270426485},
{"learn":[0.3631533299],"iteration":903,"passed_time":11.83900508,"remaining_time":1.257239478},
{"learn":[0.362960203],"iteration":904,"passed_time":11.85069937,"remaining_time":1.243996067},
{"learn":[0.3627353921],"iteration":905,"passed_time":11.86279029,"remaining_time":1.230797227},
{"learn":[0.3625351754],"iteration":906,"passed_time":11.87535177,"remaining_time":1.217649079},
{"learn":[0.362250776],"iteration":907,"passed_time":11.88742993,"remaining_time":1.204453253},
{"learn":[0.3619415726],"iteration":908,"passed_time":11.89886126,"remaining_time":1.191195131},
{"learn":[0.3618963212],"iteration":909,"passed_time":11.91122346,"remaining_time":1.17803309},
{"learn":[0.3616133607],"iteration":910,"passed_time":11.92472743,"remaining_time":1.164984348},
{"learn":[0.3613165478],"iteration":911,"passed_time":11.95154194,"remaining_time":1.153218959},
{"learn":[0.3610699983],"iteration":912,"passed_time":11.96195858,"remaining_time":1.139858046},
{"learn":[0.360833902],"iteration":913,"passed_time":11.97753137,"remaining_time":1.126988729},
{"learn":[0.3605539657],"iteration":914,"passed_time":11.99198789,"remaining_time":1.114009804},
{"learn":[0.3602165446],"iteration":915,"passed_time":12.00504528,"remaining_time":1.100899349},
{"learn":[0.3598474357],"iteration":916,"passed_time":12.01743959,"remaining_time":1.087728992},
{"learn":[0.3595524224],"iteration":917,"passed_time":12.02998949,"remaining_time":1.074574225},
{"learn":[0.3593163874],"iteration":918,"passed_time":12.04337497,"remaining_time":1.061494421},
{"learn":[0.3591221118],"iteration":919,"passed_time":12.05670647,"remaining_time":1.048409258},
{"learn":[0.3588365201],"iteration":920,"passed_time":12.06974573,"remaining_time":1.035298493},
{"learn":[0.3585430988],"iteration":921,"passed_time":12.08316377,"remaining_time":1.022219928},
{"learn":[0.35832564],"iteration":922,"passed_time":12.0949335,"remaining_time":1.009003119},
{"learn":[0.3580273871],"iteration":923,"passed_time":12.12198459,"remaining_time":0.9970463519},
{"learn":[0.3578749242],"iteration":924,"passed_time":12.1342782,"remaining_time":0.9838603945},
{"learn":[0.3575993174],"iteration":925,"passed_time":12.14651263,"remaining_time":0.9706716358},
{"learn":[0.3573541811],"iteration":926,"passed_time":12.15882137,"remaining_time":0.9574907876},
{"learn":[0.3570109432],"iteration":927,"passed_time":12.17113237,"remaining_time":0.9443119944},
{"learn":[0.3566975486],"iteration":928,"passed_time":12.18387522,"remaining_time":0.9311680735},
{"learn":[0.3563902101],"iteration":929,"passed_time":12.19551086,"remaining_time":0.9179416774},
{"learn":[0.3561165832],"iteration":930,"passed_time":12.21310146,"remaining_time":0.9051600437},
{"learn":[0.3558447262],"iteration":931,"passed_time":12.22412828,"remaining_time":0.891889188},
{"learn":[0.3554855413],"iteration":932,"passed_time":12.23715068,"remaining_time":0.8787664478},
{"learn":[0.355264512],"iteration":933,"passed_time":12.24848117,"remaining_time":0.8655243657},
{"learn":[0.3549017809],"iteration":934,"passed_time":12.26078077,"remaining_time":0.8523537435},
{"learn":[0.3546439764],"iteration":935,"passed_time":12.27456197,"remaining_time":0.8392862886},
{"learn":[0.3543589983],"iteration":936,"passed_time":12.28638168,"remaining_time":0.826085428},
{"learn":[0.354050915],"iteration":937,"passed_time":12.29802259,"remaining_time":0.8128756934},
{"learn":[0.3537784146],"iteration":938,"passed_time":12.30965579,"remaining_time":0.7996687997},
{"learn":[0.3534744438],"iteration":939,"passed_time":12.32211378,"remaining_time":0.7865179007},
{"learn":[0.3531508739],"iteration":940,"passed_time":12.33491291,"remaining_time":0.7733898639},
{"learn":[0.352834534],"iteration":941,"passed_time":12.34815203,"remaining_time":0.7602896156},
{"learn":[0.3525346446],"iteration":942,"passed_time":12.36036771,"remaining_time":0.7471272103},
{"learn":[0.3522572616],"iteration":943,"passed_time":12.37267215,"remaining_time":0.7339720764},
{"learn":[0.3519453304],"iteration":944,"passed_time":12.38490664,"remaining_time":0.7208146721},
{"learn":[0.3516748539],"iteration":945,"passed_time":12.39707505,"remaining_time":0.7076554468},
{"learn":[0.3514972983],"iteration":946,"passed_time":12.40875492,"remaining_time":0.6944709723},
{"learn":[0.35138883],"iteration":947,"passed_time":12.42045308,"remaining_time":0.6812906752},
{"learn":[0.3513549366],"iteration":948,"passed_time":12.43182119,"remaining_time":0.6680957648},
{"learn":[0.3511067588],"iteration":949,"passed_time":12.44348737,"remaining_time":0.654920388},
{"learn":[0.3509136414],"iteration":950,"passed_time":12.45529189,"remaining_time":0.641755313},
{"learn":[0.3506485526],"iteration":951,"passed_time":12.46739353,"remaining_time":0.6286080774},
{"learn":[0.3504617126],"iteration":952,"passed_time":12.47969391,"remaining_time":0.6154728373},
{"learn":[0.3502824692],"iteration":953,"passed_time":12.49116359,"remaining_time":0.6022992927},
{"learn":[0.3499512951],"iteration":954,"passed_time":12.50271482,"remaining_time":0.589133159},
{"learn":[0.3495771901],"iteration":955,"passed_time":12.51618804,"remaining_time":0.5760588635},
{"learn":[0.3494518955],"iteration":956,"passed_time":12.52810163,"remaining_time":0.5629136573},
{"learn":[0.3491181458],"iteration":957,"passed_time":12.53900533,"remaining_time":0.549726747},
{"learn":[0.3488631442],"iteration":958,"passed_time":12.55198254,"remaining_time":0.5366332471},
{"learn":[0.3486489187],"iteration":959,"passed_time":12.56475923,"remaining_time":0.5235316346},
{"learn":[0.3483949577],"iteration":960,"passed_time":12.57702606,"remaining_time":0.5104100065},
{"learn":[0.3483707447],"iteration":961,"passed_time":12.58799489,"remaining_time":0.4972388834},
{"learn":[0.3480450801],"iteration":962,"passed_time":12.60039656,"remaining_time":0.4841273861},
{"learn":[0.3478681391],"iteration":963,"passed_time":12.61265388,"remaining_time":0.4710119707},
{"learn":[0.3476201676],"iteration":964,"passed_time":12.62498804,"remaining_time":0.4579011206},
{"learn":[0.3474328929],"iteration":965,"passed_time":12.63654382,"remaining_time":0.4447644824},
{"learn":[0.3471160114],"iteration":966,"passed_time":12.67973146,"remaining_time":0.4327105874},
{"learn":[0.3468014893],"iteration":967,"passed_time":12.69174392,"remaining_time":0.4195617825},
{"learn":[0.3466125803],"iteration":968,"passed_time":12.70270997,"remaining_time":0.4063818463},
{"learn":[0.3463770161],"iteration":969,"passed_time":12.71384603,"remaining_time":0.3932117328},
{"learn":[0.346179133],"iteration":970,"passed_time":12.72625721,"remaining_time":0.380083892},
{"learn":[0.3458791972],"iteration":971,"passed_time":12.73822194,"remaining_time":0.3669446649},
{"learn":[0.3458552673],"iteration":972,"passed_time":12.74960518,"remaining_time":0.3537917162},
{"learn":[0.3455562592],"iteration":973,"passed_time":12.76321197,"remaining_time":0.340701757},
{"learn":[0.3452430558],"iteration":974,"passed_time":12.77563138,"remaining_time":0.3275802917},
{"learn":[0.344855699],"iteration":975,"passed_time":12.78680542,"remaining_time":0.3144296414},
{"learn":[0.3444694747],"iteration":976,"passed_time":12.79961153,"remaining_time":0.3013214586},
{"learn":[0.3442360707],"iteration":977,"passed_time":12.81247838,"remaining_time":0.28821526},
{"learn":[0.3439980406],"iteration":978,"passed_time":12.8248594,"remaining_time":0.275099129},
{"learn":[0.3437646841],"iteration":979,"passed_time":12.83623731,"remaining_time":0.2619640267},
{"learn":[0.3434757578],"iteration":980,"passed_time":12.84774129,"remaining_time":0.2488349485},
{"learn":[0.3432897786],"iteration":981,"passed_time":12.8609068,"remaining_time":0.2357396359},
{"learn":[0.3430591765],"iteration":982,"passed_time":12.87460144,"remaining_time":0.222653331},
{"learn":[0.3427510307],"iteration":983,"passed_time":12.88639604,"remaining_time":0.209534895},
{"learn":[0.3425046799],"iteration":984,"passed_time":12.89754781,"remaining_time":0.1964093575},
{"learn":[0.3422008343],"iteration":985,"passed_time":12.90986291,"remaining_time":0.1833043415},
{"learn":[0.3419416925],"iteration":986,"passed_time":12.92210571,"remaining_time":0.1701999739},
{"learn":[0.3416204945],"iteration":987,"passed_time":12.93308865,"remaining_time":0.1570820484},
{"learn":[0.3413318598],"iteration":988,"passed_time":12.96925965,"remaining_time":0.1442485907},
{"learn":[0.340975883],"iteration":989,"passed_time":12.98149768,"remaining_time":0.1311262392},
{"learn":[0.3406886356],"iteration":990,"passed_time":12.99275423,"remaining_time":0.1179967589},
{"learn":[0.3403017843],"iteration":991,"passed_time":13.00586845,"remaining_time":0.1048860359},
{"learn":[0.3399839154],"iteration":992,"passed_time":13.01771517,"remaining_time":0.09176637082},
{"learn":[0.3397173575],"iteration":993,"passed_time":13.0298837,"remaining_time":0.07865120947},
{"learn":[0.3396017114],"iteration":994,"passed_time":13.04256538,"remaining_time":0.06554052953},
{"learn":[0.3392024881],"iteration":995,"passed_time":13.05553011,"remaining_time":0.05243184785},
{"learn":[0.3388871168],"iteration":996,"passed_time":13.06810663,"remaining_time":0.03932228674},
{"learn":[0.3386103755],"iteration":997,"passed_time":13.08061563,"remaining_time":0.02621365858},
{"learn":[0.3382924241],"iteration":998,"passed_time":13.09471582,"remaining_time":0.01310782365},
{"learn":[0.3380327935],"iteration":999,"passed_time":13.10752423,"remaining_time":0}
]}